Workbook

Sheet Lançamentos
A1: Código | B1: Ponto Recebimento | C1: Data de Cadastro | D1: Data de Competência | E1: Modo Pagamento | F1: Histórico | G1: Usuário | H1: Plano de Contas | I1: Entrada | J1: Saída | K1: Categoria DRE
A2: 69697 | B2: Sicredi SNI | C2: 30/06/2026 | D2: 30/06/2026 | E2: PIX | F2: Boleto "55644" do cliente "IVAN LUCAS GALDINO" | G2: system | H2: 02.03.02.01 : Cobrança Bancaria | J2: -0.49 | K2: =IF(H2="02.09 : Outras Saídas", IF(OR(ISNUMBER(SEARCH("CHEQUE COMPE SICREDI", F2)), ISNUMBER(SEARCH("aniversario", F2)), ISNUMBER(SEARCH("churrasco", F2)), ISNUMBER(SEARCH("bolo", F2)), ISNUMBER(SEARCH("SUPERMERCADO", F2))), "6.1 Despesas Administrativas (Pessoal)", IF(OR(ISNUMBER(SEARCH("DLKNET", F2)), ISNUMBER(SEARCH("TESTE", F2))), "6.1 Despesas Administrativas (Gerais)", IFERROR(VLOOKUP(H2, De_Para!A:B, 2, FALSE), "NÃO MAPEADO"))), IFERROR(VLOOKUP(H2, De_Para!A:B, 2, FALSE), "NÃO MAPEADO"))
A3: 69696 | B3: Sicredi SNI | C3: 30/06/2026 | D3: 30/06/2026 | E3: PIX | F3: Boleto "55644" do cliente "IVAN LUCAS GALDINO" | G3: system | H3: 01.01.01 : Mensalidade | I3: 105 | K3: =IF(H3="02.09 : Outras Saídas", IF(OR(ISNUMBER(SEARCH("CHEQUE COMPE SICREDI", F3)), ISNUMBER(SEARCH("aniversario", F3)), ISNUMBER(SEARCH("churrasco", F3)), ISNUMBER(SEARCH("bolo", F3)), ISNUMBER(SEARCH("SUPERMERCADO", F3))), "6.1 Despesas Administrativas (Pessoal)", IF(OR(ISNUMBER(SEARCH("DLKNET", F3)), ISNUMBER(SEARCH("TESTE", F3))), "6.1 Despesas Administrativas (Gerais)", IFERROR(VLOOKUP(H3, De_Para!A:B, 2, FALSE), "NÃO MAPEADO"))), IFERROR(VLOOKUP(H3, De_Para!A:B, 2, FALSE), "NÃO MAPEADO"))
A4: 69695 | B4: Sicredi SNI | C4: 30/06/2026 | D4: 30/06/2026 | E4: PIX | F4: Boleto "67630" do cliente "RAFAEL APARECIDO DE SOUZA" | G4: system | H4: 02.03.02.01 : Cobrança Bancaria | J4: -0.49 | K4: =IF(H4="02.09 : Outras Saídas", IF(OR(ISNUMBER(SEARCH("CHEQUE COMPE SICREDI", F4)), ISNUMBER(SEARCH("aniversario", F4)), ISNUMBER(SEARCH("churrasco", F4)), ISNUMBER(SEARCH("bolo", F4)), ISNUMBER(SEARCH("SUPERMERCADO", F4))), "6.1 Despesas Administrativas (Pessoal)", IF(OR(ISNUMBER(SEARCH("DLKNET", F4)), ISNUMBER(SEARCH("TESTE", F4))), "6.1 Despesas Administrativas (Gerais)", IFERROR(VLOOKUP(H4, De_Para!A:B, 2, FALSE), "NÃO MAPEADO"))), IFERROR(VLOOKUP(H4, De_Para!A:B, 2, FALSE), "NÃO MAPEADO"))
A5: 69694 | B5: Sicredi SNI | C5: 30/06/2026 | D5: 30/06/2026 | E5: PIX | F5: Boleto "67630" do cliente "RAFAEL APARECIDO DE SOUZA" | G5: system | H5: 01.01.01 : Mensalidade | I5: 109.9 | K5: =IF(H5="02.09 : Outras Saídas", IF(OR(ISNUMBER(SEARCH("CHEQUE COMPE SICREDI", F5)), ISNUMBER(SEARCH("aniversario", F5)), ISNUMBER(SEARCH("churrasco", F5)), ISNUMBER(SEARCH("bolo", F5)), ISNUMBER(SEARCH("SUPERMERCADO", F5))), "6.1 Despesas Administrativas (Pessoal)", IF(OR(ISNUMBER(SEARCH("DLKNET", F5)), ISNUMBER(SEARCH("TESTE", F5))), "6.1 Despesas Administrativas (Gerais)", IFERROR(VLOOKUP(H5, De_Para!A:B, 2, FALSE), "NÃO MAPEADO"))), IFERROR(VLOOKUP(H5, De_Para!A:B, 2, FALSE), "NÃO MAPEADO"))
A6: 69693 | B6: Sicredi SNI | C6: 30/06/2026 | D6: 30/06/2026 | E6: PIX | F6: Boleto "67752" do cliente "DARIO OLIVEIRA" | G6: system | H6: 02.03.02.01 : Cobrança Bancaria | J6: -0.49 | K6: =IF(H6="02.09 : Outras Saídas", IF(OR(ISNUMBER(SEARCH("CHEQUE COMPE SICREDI", F6)), ISNUMBER(SEARCH("aniversario", F6)), ISNUMBER(SEARCH("churrasco", F6)), ISNUMBER(SEARCH("bolo", F6)), ISNUMBER(SEARCH("SUPERMERCADO", F6))), "6.1 Despesas Administrativas (Pessoal)", IF(OR(ISNUMBER(SEARCH("DLKNET", F6)), ISNUMBER(SEARCH("TESTE", F6))), "6.1 Despesas Administrativas (Gerais)", IFERROR(VLOOKUP(H6, De_Para!A:B, 2, FALSE), "NÃO MAPEADO"))), IFERROR(VLOOKUP(H6, De_Para!A:B, 2, FALSE), "NÃO MAPEADO"))
A7: 69692 | B7: Sicredi SNI | C7: 30/06/2026 | D7: 30/06/2026 | E7: PIX | F7: Boleto "67752" do cliente "DARIO OLIVEIRA" | G7: system | H7: 01.01.01 : Mensalidade | I7: 104.9 | K7: =IF(H7="02.09 : Outras Saídas", IF(OR(ISNUMBER(SEARCH("CHEQUE COMPE SICREDI", F7)), ISNUMBER(SEARCH("aniversario", F7)), ISNUMBER(SEARCH("churrasco", F7)), ISNUMBER(SEARCH("bolo", F7)), ISNUMBER(SEARCH("SUPERMERCADO", F7))), "6.1 Despesas Administrativas (Pessoal)", IF(OR(ISNUMBER(SEARCH("DLKNET", F7)), ISNUMBER(SEARCH("TESTE", F7))), "6.1 Despesas Administrativas (Gerais)", IFERROR(VLOOKUP(H7, De_Para!A:B, 2, FALSE), "NÃO MAPEADO"))), IFERROR(VLOOKUP(H7, De_Para!A:B, 2, FALSE), "NÃO MAPEADO"))
A8: 69691 | B8: Sicoob | C8: 30/06/2026 | D8: 30/06/2026 | E8: Dinheiro | F8: Boleto "63770" do cliente "JULIA ISABEL FARINCHA" | G8: system | H8: 02.03.02.01 : Cobrança Bancaria | J8: -0.88 | K8: =IF(H8="02.09 : Outras Saídas", IF(OR(ISNUMBER(SEARCH("CHEQUE COMPE SICREDI", F8)), ISNUMBER(SEARCH("aniversario", F8)), ISNUMBER(SEARCH("churrasco", F8)), ISNUMBER(SEARCH("bolo", F8)), ISNUMBER(SEARCH("SUPERMERCADO", F8))), "6.1 Despesas Administrativas (Pessoal)", IF(OR(ISNUMBER(SEARCH("DLKNET", F8)), ISNUMBER(SEARCH("TESTE", F8))), "6.1 Despesas Administrativas (Gerais)", IFERROR(VLOOKUP(H8, De_Para!A:B, 2, FALSE), "NÃO MAPEADO"))), IFERROR(VLOOKUP(H8, De_Para!A:B, 2, FALSE), "NÃO MAPEADO"))
A9: 69690 | B9: Sicoob | C9: 30/06/2026 | D9: 30/06/2026 | E9: Dinheiro | F9: Boleto "63770" do cliente "JULIA ISABEL FARINCHA" | G9: system | H9: 01.01.01 : Mensalidade | I9: 105 | K9: =IF(H9="02.09 : Outras Saídas", IF(OR(ISNUMBER(SEARCH("CHEQUE COMPE SICREDI", F9)), ISNUMBER(SEARCH("aniversario", F9)), ISNUMBER(SEARCH("churrasco", F9)), ISNUMBER(SEARCH("bolo", F9)), ISNUMBER(SEARCH("SUPERMERCADO", F9))), "6.1 Despesas Administrativas (Pessoal)", IF(OR(ISNUMBER(SEARCH("DLKNET", F9)), ISNUMBER(SEARCH("TESTE", F9))), "6.1 Despesas Administrativas (Gerais)", IFERROR(VLOOKUP(H9, De_Para!A:B, 2, FALSE), "NÃO MAPEADO"))), IFERROR(VLOOKUP(H9, De_Para!A:B, 2, FALSE), "NÃO MAPEADO"))
A10: 69689 | B10: Sicoob | C10: 30/06/2026 | D10: 30/06/2026 | E10: Dinheiro | F10: Boleto "59534" do cliente "VILCIANE APARECIDA CAMARGO" | G10: system | H10: 02.03.02.01 : Cobrança Bancaria | J10: -0.88 | K10: =IF(H10="02.09 : Outras Saídas", IF(OR(ISNUMBER(SEARCH("CHEQUE COMPE SICREDI", F10)), ISNUMBER(SEARCH("aniversario", F10)), ISNUMBER(SEARCH("churrasco", F10)), ISNUMBER(SEARCH("bolo", F10)), ISNUMBER(SEARCH("SUPERMERCADO", F10))), "6.1 Despesas Administrativas (Pessoal)", IF(OR(ISNUMBER(SEARCH("DLKNET", F10)), ISNUMBER(SEARCH("TESTE", F10))), "6.1 Despesas Administrativas (Gerais)", IFERROR(VLOOKUP(H10, De_Para!A:B, 2, FALSE), "NÃO MAPEADO"))), IFERROR(VLOOKUP(H10, De_Para!A:B, 2, FALSE), "NÃO MAPEADO"))
A11: 69688 | B11: Sicoob | C11: 30/06/2026 | D11: 30/06/2026 | E11: Dinheiro | F11: Boleto "59534" do cliente "VILCIANE APARECIDA CAMARGO" | G11: system | H11: 01.01.01 : Mensalidade | I11: 105 | K11: =IF(H11="02.09 : Outras Saídas", IF(OR(ISNUMBER(SEARCH("CHEQUE COMPE SICREDI", F11)), ISNUMBER(SEARCH("aniversario", F11)), ISNUMBER(SEARCH("churrasco", F11)), ISNUMBER(SEARCH("bolo", F11)), ISNUMBER(SEARCH("SUPERMERCADO", F11))), "6.1 Despesas Administrativas (Pessoal)", IF(OR(ISNUMBER(SEARCH("DLKNET", F11)), ISNUMBER(SEARCH("TESTE", F11))), "6.1 Despesas Administrativas (Gerais)", IFERROR(VLOOKUP(H11, De_Para!A:B, 2, FALSE), "NÃO MAPEADO"))), IFERROR(VLOOKUP(H11, De_Para!A:B, 2, FALSE), "NÃO MAPEADO"))
A12: 69687 | B12: Sicoob | C12: 30/06/2026 | D12: 30/06/2026 | E12: Dinheiro | F12: Boleto "59513" do cliente "MARCOS SOUZA ESPLUGUES" | G12: system | H12: 02.03.02.01 : Cobrança Bancaria | J12: -0.88 | K12: =IF(H12="02.09 : Outras Saídas", IF(OR(ISNUMBER(SEARCH("CHEQUE COMPE SICREDI", F12)), ISNUMBER(SEARCH("aniversario", F12)), ISNUMBER(SEARCH("churrasco", F12)), ISNUMBER(SEARCH("bolo", F12)), ISNUMBER(SEARCH("SUPERMERCADO", F12))), "6.1 Despesas Administrativas (Pessoal)", IF(OR(ISNUMBER(SEARCH("DLKNET", F12)), ISNUMBER(SEARCH("TESTE", F12))), "6.1 Despesas Administrativas (Gerais)", IFERROR(VLOOKUP(H12, De_Para!A:B, 2, FALSE), "NÃO MAPEADO"))), IFERROR(VLOOKUP(H12, De_Para!A:B, 2, FALSE), "NÃO MAPEADO"))
A13: 69686 | B13: Sicoob | C13: 30/06/2026 | D13: 30/06/2026 | E13: Dinheiro | F13: Boleto "59513" do cliente "MARCOS SOUZA ESPLUGUES" | G13: system | H13: 01.01.01 : Mensalidade | I13: 105 | K13: =IF(H13="02.09 : Outras Saídas", IF(OR(ISNUMBER(SEARCH("CHEQUE COMPE SICREDI", F13)), ISNUMBER(SEARCH("aniversario", F13)), ISNUMBER(SEARCH("churrasco", F13)), ISNUMBER(SEARCH("bolo", F13)), ISNUMBER(SEARCH("SUPERMERCADO", F13))), "6.1 Despesas Administrativas (Pessoal)", IF(OR(ISNUMBER(SEARCH("DLKNET", F13)), ISNUMBER(SEARCH("TESTE", F13))), "6.1 Despesas Administrativas (Gerais)", IFERROR(VLOOKUP(H13, De_Para!A:B, 2, FALSE), "NÃO MAPEADO"))), IFERROR(VLOOKUP(H13, De_Para!A:B, 2, FALSE), "NÃO MAPEADO"))
A14: 69685 | B14: Sicredi SNI | C14: 30/06/2026 | D14: 30/06/2026 | E14: Dinheiro | F14: Boleto "67762" do cliente "JOSE CARLOS DE LIMA" | G14: system | H14: 02.03.02.01 : Cobrança Bancaria | J14: -1.08 | K14: =IF(H14="02.09 : Outras Saídas", IF(OR(ISNUMBER(SEARCH("CHEQUE COMPE SICREDI", F14)), ISNUMBER(SEARCH("aniversario", F14)), ISNUMBER(SEARCH("churrasco", F14)), ISNUMBER(SEARCH("bolo", F14)), ISNUMBER(SEARCH("SUPERMERCADO", F14))), "6.1 Despesas Administrativas (Pessoal)", IF(OR(ISNUMBER(SEARCH("DLKNET", F14)), ISNUMBER(SEARCH("TESTE", F14))), "6.1 Despesas Administrativas (Gerais)", IFERROR(VLOOKUP(H14, De_Para!A:B, 2, FALSE), "NÃO MAPEADO"))), IFERROR(VLOOKUP(H14, De_Para!A:B, 2, FALSE), "NÃO MAPEADO"))
A15: 69684 | B15: Sicredi SNI | C15: 30/06/2026 | D15: 30/06/2026 | E15: Dinheiro | F15: Boleto "67762" do cliente "JOSE CARLOS DE LIMA" | G15: system | H15: 01.01.01 : Mensalidade | I15: 80 | K15: =IF(H15="02.09 : Outras Saídas", IF(OR(ISNUMBER(SEARCH("CHEQUE COMPE SICREDI", F15)), ISNUMBER(SEARCH("aniversario", F15)), ISNUMBER(SEARCH("churrasco", F15)), ISNUMBER(SEARCH("bolo", F15)), ISNUMBER(SEARCH("SUPERMERCADO", F15))), "6.1 Despesas Administrativas (Pessoal)", IF(OR(ISNUMBER(SEARCH("DLKNET", F15)), ISNUMBER(SEARCH("TESTE", F15))), "6.1 Despesas Administrativas (Gerais)", IFERROR(VLOOKUP(H15, De_Para!A:B, 2, FALSE), "NÃO MAPEADO"))), IFERROR(VLOOKUP(H15, De_Para!A:B, 2, FALSE), "NÃO MAPEADO"))
A16: 69683 | B16: Sicredi SNI | C16: 30/06/2026 | D16: 30/06/2026 | E16: Dinheiro | F16: Boleto "67153" do cliente "VANDA APARECIDA CAMARGO" | G16: system | H16: 02.03.02.01 : Cobrança Bancaria | J16: -1.08 | K16: =IF(H16="02.09 : Outras Saídas", IF(OR(ISNUMBER(SEARCH("CHEQUE COMPE SICREDI", F16)), ISNUMBER(SEARCH("aniversario", F16)), ISNUMBER(SEARCH("churrasco", F16)), ISNUMBER(SEARCH("bolo", F16)), ISNUMBER(SEARCH("SUPERMERCADO", F16))), "6.1 Despesas Administrativas (Pessoal)", IF(OR(ISNUMBER(SEARCH("DLKNET", F16)), ISNUMBER(SEARCH("TESTE", F16))), "6.1 Despesas Administrativas (Gerais)", IFERROR(VLOOKUP(H16, De_Para!A:B, 2, FALSE), "NÃO MAPEADO"))), IFERROR(VLOOKUP(H16, De_Para!A:B, 2, FALSE), "NÃO MAPEADO"))
A17: 69682 | B17: Sicredi SNI | C17: 30/06/2026 | D17: 30/06/2026 | E17: Dinheiro | F17: Boleto "67153" do cliente "VANDA APARECIDA CAMARGO" | G17: system | H17: 01.01.01 : Mensalidade | I17: 112.41 | K17: =IF(H17="02.09 : Outras Saídas", IF(OR(ISNUMBER(SEARCH("CHEQUE COMPE SICREDI", F17)), ISNUMBER(SEARCH("aniversario", F17)), ISNUMBER(SEARCH("churrasco", F17)), ISNUMBER(SEARCH("bolo", F17)), ISNUMBER(SEARCH("SUPERMERCADO", F17))), "6.1 Despesas Administrativas (Pessoal)", IF(OR(ISNUMBER(SEARCH("DLKNET", F17)), ISNUMBER(SEARCH("TESTE", F17))), "6.1 Despesas Administrativas (Gerais)", IFERROR(VLOOKUP(H17, De_Para!A:B, 2, FALSE), "NÃO MAPEADO"))), IFERROR(VLOOKUP(H17, De_Para!A:B, 2, FALSE), "NÃO MAPEADO"))
A18: 69681 | B18: Sicoob | C18: 30/06/2026 | D18: 30/06/2026 | E18: Dinheiro | F18: Boleto "66152" do cliente "VALMIR TEODORO LEITE" | G18: system | H18: 02.03.02.01 : Cobrança Bancaria | J18: -0.88 | K18: =IF(H18="02.09 : Outras Saídas", IF(OR(ISNUMBER(SEARCH("CHEQUE COMPE SICREDI", F18)), ISNUMBER(SEARCH("aniversario", F18)), ISNUMBER(SEARCH("churrasco", F18)), ISNUMBER(SEARCH("bolo", F18)), ISNUMBER(SEARCH("SUPERMERCADO", F18))), "6.1 Despesas Administrativas (Pessoal)", IF(OR(ISNUMBER(SEARCH("DLKNET", F18)), ISNUMBER(SEARCH("TESTE", F18))), "6.1 Despesas Administrativas (Gerais)", IFERROR(VLOOKUP(H18, De_Para!A:B, 2, FALSE), "NÃO MAPEADO"))), IFERROR(VLOOKUP(H18, De_Para!A:B, 2, FALSE), "NÃO MAPEADO"))
A19: 69680 | B19: Sicoob | C19: 30/06/2026 | D19: 30/06/2026 | E19: Dinheiro | F19: Boleto "66152" do cliente "VALMIR TEODORO LEITE" | G19: system | H19: 01.03.01 : Mensalidade | I19: 107.45 | K19: =IF(H19="02.09 : Outras Saídas", IF(OR(ISNUMBER(SEARCH("CHEQUE COMPE SICREDI", F19)), ISNUMBER(SEARCH("aniversario", F19)), ISNUMBER(SEARCH("churrasco", F19)), ISNUMBER(SEARCH("bolo", F19)), ISNUMBER(SEARCH("SUPERMERCADO", F19))), "6.1 Despesas Administrativas (Pessoal)", IF(OR(ISNUMBER(SEARCH("DLKNET", F19)), ISNUMBER(SEARCH("TESTE", F19))), "6.1 Despesas Administrativas (Gerais)", IFERROR(VLOOKUP(H19, De_Para!A:B, 2, FALSE), "NÃO MAPEADO"))), IFERROR(VLOOKUP(H19, De_Para!A:B, 2, FALSE), "NÃO MAPEADO"))
A20: 69679 | B20: Sicoob | C20: 30/06/2026 | D20: 30/06/2026 | E20: Dinheiro | F20: Boleto "65405" do cliente "JOSE HUGO BRUNHARI" | G20: system | H20: 02.03.02.01 : Cobrança Bancaria | J20: -0.88 | K20: =IF(H20="02.09 : Outras Saídas", IF(OR(ISNUMBER(SEARCH("CHEQUE COMPE SICREDI", F20)), ISNUMBER(SEARCH("aniversario", F20)), ISNUMBER(SEARCH("churrasco", F20)), ISNUMBER(SEARCH("bolo", F20)), ISNUMBER(SEARCH("SUPERMERCADO", F20))), "6.1 Despesas Administrativas (Pessoal)", IF(OR(ISNUMBER(SEARCH("DLKNET", F20)), ISNUMBER(SEARCH("TESTE", F20))), "6.1 Despesas Administrativas (Gerais)", IFERROR(VLOOKUP(H20, De_Para!A:B, 2, FALSE), "NÃO MAPEADO"))), IFERROR(VLOOKUP(H20, De_Para!A:B, 2, FALSE), "NÃO MAPEADO"))
A21: 69678 | B21: Sicoob | C21: 30/06/2026 | D21: 30/06/2026 | E21: Dinheiro | F21: Boleto "65405" do cliente "JOSE HUGO BRUNHARI" | G21: system | H21: 01.01.01 : Mensalidade | I21: 99.9 | K21: =IF(H21="02.09 : Outras Saídas", IF(OR(ISNUMBER(SEARCH("CHEQUE COMPE SICREDI", F21)), ISNUMBER(SEARCH("aniversario", F21)), ISNUMBER(SEARCH("churrasco", F21)), ISNUMBER(SEARCH("bolo", F21)), ISNUMBER(SEARCH("SUPERMERCADO", F21))), "6.1 Despesas Administrativas (Pessoal)", IF(OR(ISNUMBER(SEARCH("DLKNET", F21)), ISNUMBER(SEARCH("TESTE", F21))), "6.1 Despesas Administrativas (Gerais)", IFERROR(VLOOKUP(H21, De_Para!A:B, 2, FALSE), "NÃO MAPEADO"))), IFERROR(VLOOKUP(H21, De_Para!A:B, 2, FALSE), "NÃO MAPEADO"))
A22: 69677 | B22: Sicoob | C22: 30/06/2026 | D22: 30/06/2026 | E22: Dinheiro | F22: Boleto "64675" do cliente "ADILSON SILVIO AMBROSIO" | G22: system | H22: 02.03.02.01 : Cobrança Bancaria | J22: -0.88 | K22: =IF(H22="02.09 : Outras Saídas", IF(OR(ISNUMBER(SEARCH("CHEQUE COMPE SICREDI", F22)), ISNUMBER(SEARCH("aniversario", F22)), ISNUMBER(SEARCH("churrasco", F22)), ISNUMBER(SEARCH("bolo", F22)), ISNUMBER(SEARCH("SUPERMERCADO", F22))), "6.1 Despesas Administrativas (Pessoal)", IF(OR(ISNUMBER(SEARCH("DLKNET", F22)), ISNUMBER(SEARCH("TESTE", F22))), "6.1 Despesas Administrativas (Gerais)", IFERROR(VLOOKUP(H22, De_Para!A:B, 2, FALSE), "NÃO MAPEADO"))), IFERROR(VLOOKUP(H22, De_Para!A:B, 2, FALSE), "NÃO MAPEADO"))
A23: 69676 | B23: Sicoob | C23: 30/06/2026 | D23: 30/06/2026 | E23: Dinheiro | F23: Boleto "64675" do cliente "ADILSON SILVIO AMBROSIO" | G23: system | H23: 01.01.01 : Mensalidade | I23: 107.51 | K23: =IF(H23="02.09 : Outras Saídas", IF(OR(ISNUMBER(SEARCH("CHEQUE COMPE SICREDI", F23)), ISNUMBER(SEARCH("aniversario", F23)), ISNUMBER(SEARCH("churrasco", F23)), ISNUMBER(SEARCH("bolo", F23)), ISNUMBER(SEARCH("SUPERMERCADO", F23))), "6.1 Despesas Administrativas (Pessoal)", IF(OR(ISNUMBER(SEARCH("DLKNET", F23)), ISNUMBER(SEARCH("TESTE", F23))), "6.1 Despesas Administrativas (Gerais)", IFERROR(VLOOKUP(H23, De_Para!A:B, 2, FALSE), "NÃO MAPEADO"))), IFERROR(VLOOKUP(H23, De_Para!A:B, 2, FALSE), "NÃO MAPEADO"))
A24: 69675 | B24: Sicoob | C24: 30/06/2026 | D24: 30/06/2026 | E24: Dinheiro | F24: Boleto "62711" do cliente "JOSE CANDIDO DA ROSA" | G24: system | H24: 02.03.02.01 : Cobrança Bancaria | J24: -0.88 | K24: =IF(H24="02.09 : Outras Saídas", IF(OR(ISNUMBER(SEARCH("CHEQUE COMPE SICREDI", F24)), ISNUMBER(SEARCH("aniversario", F24)), ISNUMBER(SEARCH("churrasco", F24)), ISNUMBER(SEARCH("bolo", F24)), ISNUMBER(SEARCH("SUPERMERCADO", F24))), "6.1 Despesas Administrativas (Pessoal)", IF(OR(ISNUMBER(SEARCH("DLKNET", F24)), ISNUMBER(SEARCH("TESTE", F24))), "6.1 Despesas Administrativas (Gerais)", IFERROR(VLOOKUP(H24, De_Para!A:B, 2, FALSE), "NÃO MAPEADO"))), IFERROR(VLOOKUP(H24, De_Para!A:B, 2, FALSE), "NÃO MAPEADO"))
A25: 69674 | B25: Sicoob | C25: 30/06/2026 | D25: 30/06/2026 | E25: Dinheiro | F25: Boleto "62711" do cliente "JOSE CANDIDO DA ROSA" | G25: system | H25: 01.01.01 : Mensalidade | I25: 109.9 | K25: =IF(H25="02.09 : Outras Saídas", IF(OR(ISNUMBER(SEARCH("CHEQUE COMPE SICREDI", F25)), ISNUMBER(SEARCH("aniversario", F25)), ISNUMBER(SEARCH("churrasco", F25)), ISNUMBER(SEARCH("bolo", F25)), ISNUMBER(SEARCH("SUPERMERCADO", F25))), "6.1 Despesas Administrativas (Pessoal)", IF(OR(ISNUMBER(SEARCH("DLKNET", F25)), ISNUMBER(SEARCH("TESTE", F25))), "6.1 Despesas Administrativas (Gerais)", IFERROR(VLOOKUP(H25, De_Para!A:B, 2, FALSE), "NÃO MAPEADO"))), IFERROR(VLOOKUP(H25, De_Para!A:B, 2, FALSE), "NÃO MAPEADO"))
A26: 69673 | B26: Sicoob | C26: 30/06/2026 | D26: 30/06/2026 | E26: Dinheiro | F26: Boleto "61154" do cliente "ELAINE TUONO DE OLIVEIRA SANTOS" | G26: system | H26: 02.03.02.01 : Cobrança Bancaria | J26: -0.88 | K26: =IF(H26="02.09 : Outras Saídas", IF(OR(ISNUMBER(SEARCH("CHEQUE COMPE SICREDI", F26)), ISNUMBER(SEARCH("aniversario", F26)), ISNUMBER(SEARCH("churrasco", F26)), ISNUMBER(SEARCH("bolo", F26)), ISNUMBER(SEARCH("SUPERMERCADO", F26))), "6.1 Despesas Administrativas (Pessoal)", IF(OR(ISNUMBER(SEARCH("DLKNET", F26)), ISNUMBER(SEARCH("TESTE", F26))), "6.1 Despesas Administrativas (Gerais)", IFERROR(VLOOKUP(H26, De_Para!A:B, 2, FALSE), "NÃO MAPEADO"))), IFERROR(VLOOKUP(H26, De_Para!A:B, 2, FALSE), "NÃO MAPEADO"))
A27: 69672 | B27: Sicoob | C27: 30/06/2026 | D27: 30/06/2026 | E27: Dinheiro | F27: Boleto "61154" do cliente "ELAINE TUONO DE OLIVEIRA SANTOS" | G27: system | H27: 01.03.01 : Mensalidade | I27: 107.8 | K27: =IF(H27="02.09 : Outras Saídas", IF(OR(ISNUMBER(SEARCH("CHEQUE COMPE SICREDI", F27)), ISNUMBER(SEARCH("aniversario", F27)), ISNUMBER(SEARCH("churrasco", F27)), ISNUMBER(SEARCH("bolo", F27)), ISNUMBER(SEARCH("SUPERMERCADO", F27))), "6.1 Despesas Administrativas (Pessoal)", IF(OR(ISNUMBER(SEARCH("DLKNET", F27)), ISNUMBER(SEARCH("TESTE", F27))), "6.1 Despesas Administrativas (Gerais)", IFERROR(VLOOKUP(H27, De_Para!A:B, 2, FALSE), "NÃO MAPEADO"))), IFERROR(VLOOKUP(H27, De_Para!A:B, 2, FALSE), "NÃO MAPEADO"))
A28: 69671 | B28: Sicoob | C28: 30/06/2026 | D28: 30/06/2026 | E28: Dinheiro | F28: Boleto "55145" do cliente "TIAGO APARECIDO DA SILVA" | G28: system | H28: 02.03.02.01 : Cobrança Bancaria | J28: -0.88 | K28: =IF(H28="02.09 : Outras Saídas", IF(OR(ISNUMBER(SEARCH("CHEQUE COMPE SICREDI", F28)), ISNUMBER(SEARCH("aniversario", F28)), ISNUMBER(SEARCH("churrasco", F28)), ISNUMBER(SEARCH("bolo", F28)), ISNUMBER(SEARCH("SUPERMERCADO", F28))), "6.1 Despesas Administrativas (Pessoal)", IF(OR(ISNUMBER(SEARCH("DLKNET", F28)), ISNUMBER(SEARCH("TESTE", F28))), "6.1 Despesas Administrativas (Gerais)", IFERROR(VLOOKUP(H28, De_Para!A:B, 2, FALSE), "NÃO MAPEADO"))), IFERROR(VLOOKUP(H28, De_Para!A:B, 2, FALSE), "NÃO MAPEADO"))
A29: 69670 | B29: Sicoob | C29: 30/06/2026 | D29: 30/06/2026 | E29: Dinheiro | F29: Boleto "55145" do cliente "TIAGO APARECIDO DA SILVA" | G29: system | H29: 01.01.01 : Mensalidade | I29: 107.27 | K29: =IF(H29="02.09 : Outras Saídas", IF(OR(ISNUMBER(SEARCH("CHEQUE COMPE SICREDI", F29)), ISNUMBER(SEARCH("aniversario", F29)), ISNUMBER(SEARCH("churrasco", F29)), ISNUMBER(SEARCH("bolo", F29)), ISNUMBER(SEARCH("SUPERMERCADO", F29))), "6.1 Despesas Administrativas (Pessoal)", IF(OR(ISNUMBER(SEARCH("DLKNET", F29)), ISNUMBER(SEARCH("TESTE", F29))), "6.1 Despesas Administrativas (Gerais)", IFERROR(VLOOKUP(H29, De_Para!A:B, 2, FALSE), "NÃO MAPEADO"))), IFERROR(VLOOKUP(H29, De_Para!A:B, 2, FALSE), "NÃO MAPEADO"))
A30: 69669 | B30: Sicredi SNI | C30: 30/06/2026 | D30: 30/06/2026 | E30: PIX | F30: Boleto "54988" do cliente "ALEX GOES RIBEIRO" | G30: system | H30: 02.03.02.01 : Cobrança Bancaria | J30: -0.49 | K30: =IF(H30="02.09 : Outras Saídas", IF(OR(ISNUMBER(SEARCH("CHEQUE COMPE SICREDI", F30)), ISNUMBER(SEARCH("aniversario", F30)), ISNUMBER(SEARCH("churrasco", F30)), ISNUMBER(SEARCH("bolo", F30)), ISNUMBER(SEARCH("SUPERMERCADO", F30))), "6.1 Despesas Administrativas (Pessoal)", IF(OR(ISNUMBER(SEARCH("DLKNET", F30)), ISNUMBER(SEARCH("TESTE", F30))), "6.1 Despesas Administrativas (Gerais)", IFERROR(VLOOKUP(H30, De_Para!A:B, 2, FALSE), "NÃO MAPEADO"))), IFERROR(VLOOKUP(H30, De_Para!A:B, 2, FALSE), "NÃO MAPEADO"))
A31: 69668 | B31: Sicredi SNI | C31: 30/06/2026 | D31: 30/06/2026 | E31: PIX | F31: Boleto "54988" do cliente "ALEX GOES RIBEIRO" | G31: system | H31: 01.01.01 : Mensalidade | I31: 107.45 | K31: =IF(H31="02.09 : Outras Saídas", IF(OR(ISNUMBER(SEARCH("CHEQUE COMPE SICREDI", F31)), ISNUMBER(SEARCH("aniversario", F31)), ISNUMBER(SEARCH("churrasco", F31)), ISNUMBER(SEARCH("bolo", F31)), ISNUMBER(SEARCH("SUPERMERCADO", F31))), "6.1 Despesas Administrativas (Pessoal)", IF(OR(ISNUMBER(SEARCH("DLKNET", F31)), ISNUMBER(SEARCH("TESTE", F31))), "6.1 Despesas Administrativas (Gerais)", IFERROR(VLOOKUP(H31, De_Para!A:B, 2, FALSE), "NÃO MAPEADO"))), IFERROR(VLOOKUP(H31, De_Para!A:B, 2, FALSE), "NÃO MAPEADO"))
A32: 69667 | B32: Sicoob | C32: 30/06/2026 | D32: 29/06/2026 | E32: Débito em Conta | F32: TARIFA COBRANÇA | G32: clau | H32: 02.03.03.01 : Tarifas Bancarias | J32: -5.62 | K32: =IF(H32="02.09 : Outras Saídas", IF(OR(ISNUMBER(SEARCH("CHEQUE COMPE SICREDI", F32)), ISNUMBER(SEARCH("aniversario", F32)), ISNUMBER(SEARCH("churrasco", F32)), ISNUMBER(SEARCH("bolo", F32)), ISNUMBER(SEARCH("SUPERMERCADO", F32))), "6.1 Despesas Administrativas (Pessoal)", IF(OR(ISNUMBER(SEARCH("DLKNET", F32)), ISNUMBER(SEARCH("TESTE", F32))), "6.1 Despesas Administrativas (Gerais)", IFERROR(VLOOKUP(H32, De_Para!A:B, 2, FALSE), "NÃO MAPEADO"))), IFERROR(VLOOKUP(H32, De_Para!A:B, 2, FALSE), "NÃO MAPEADO"))
A33: 69666 | B33: Sicoob | C33: 30/06/2026 | D33: 29/06/2026 | E33: PIX | F33: PIX EMITIDO OUTRA IF_x000D_ Pagamento Pix_x000D_ 04.368.898 0001-06 | G33: clau | H33: 02.03.04.07 : ALUGUEL POSTE | J33: -5929.6 | K33: =IF(H33="02.09 : Outras Saídas", IF(OR(ISNUMBER(SEARCH("CHEQUE COMPE SICREDI", F33)), ISNUMBER(SEARCH("aniversario", F33)), ISNUMBER(SEARCH("churrasco", F33)), ISNUMBER(SEARCH("bolo", F33)), ISNUMBER(SEARCH("SUPERMERCADO", F33))), "6.1 Despesas Administrativas (Pessoal)", IF(OR(ISNUMBER(SEARCH("DLKNET", F33)), ISNUMBER(SEARCH("TESTE", F33))), "6.1 Despesas Administrativas (Gerais)", IFERROR(VLOOKUP(H33, De_Para!A:B, 2, FALSE), "NÃO MAPEADO"))), IFERROR(VLOOKUP(H33, De_Para!A:B, 2, FALSE), "NÃO MAPEADO"))
A34: 69665 | B34: Sicredi SNI | C34: 30/06/2026 | D34: 30/06/2026 | E34: Débito em Conta | F34: PIX EMITIDO OUTRA IF_x000D_ Pagamento Pix_x000D_ 04.368.898 0001-06 | G34: clau | H34: 02.03.03.01 : Tarifas Bancarias | J34: -13.52 | K34: =IF(H34="02.09 : Outras Saídas", IF(OR(ISNUMBER(SEARCH("CHEQUE COMPE SICREDI", F34)), ISNUMBER(SEARCH("aniversario", F34)), ISNUMBER(SEARCH("churrasco", F34)), ISNUMBER(SEARCH("bolo", F34)), ISNUMBER(SEARCH("SUPERMERCADO", F34))), "6.1 Despesas Administrativas (Pessoal)", IF(OR(ISNUMBER(SEARCH("DLKNET", F34)), ISNUMBER(SEARCH("TESTE", F34))), "6.1 Despesas Administrativas (Gerais)", IFERROR(VLOOKUP(H34, De_Para!A:B, 2, FALSE), "NÃO MAPEADO"))), IFERROR(VLOOKUP(H34, De_Para!A:B, 2, FALSE), "NÃO MAPEADO"))
A35: 69664 | B35: Sicoob | C35: 30/06/2026 | D35: 30/06/2026 | E35: PIX | F35: PIX EMITIDO OUTRA IF - MESMA TIT._x000D_ Pagamento Pix_x000D_ 10.145.409 0001-50 | G35: clau | H35: 03.02 : TRANSFERENCIA ENTRE CONTAS | J35: -2250 | K35: =IF(H35="02.09 : Outras Saídas", IF(OR(ISNUMBER(SEARCH("CHEQUE COMPE SICREDI", F35)), ISNUMBER(SEARCH("aniversario", F35)), ISNUMBER(SEARCH("churrasco", F35)), ISNUMBER(SEARCH("bolo", F35)), ISNUMBER(SEARCH("SUPERMERCADO", F35))), "6.1 Despesas Administrativas (Pessoal)", IF(OR(ISNUMBER(SEARCH("DLKNET", F35)), ISNUMBER(SEARCH("TESTE", F35))), "6.1 Despesas Administrativas (Gerais)", IFERROR(VLOOKUP(H35, De_Para!A:B, 2, FALSE), "NÃO MAPEADO"))), IFERROR(VLOOKUP(H35, De_Para!A:B, 2, FALSE), "NÃO MAPEADO"))
A36: 69663 | B36: Sicredi SNI | C36: 30/06/2026 | D36: 30/06/2026 | E36: Dinheiro | F36: Boleto "66667" do cliente "LAURINDA DAS DORES IZIDORO" | G36: system | H36: 02.03.02.01 : Cobrança Bancaria | J36: -1.08 | K36: =IF(H36="02.09 : Outras Saídas", IF(OR(ISNUMBER(SEARCH("CHEQUE COMPE SICREDI", F36)), ISNUMBER(SEARCH("aniversario", F36)), ISNUMBER(SEARCH("churrasco", F36)), ISNUMBER(SEARCH("bolo", F36)), ISNUMBER(SEARCH("SUPERMERCADO", F36))), "6.1 Despesas Administrativas (Pessoal)", IF(OR(ISNUMBER(SEARCH("DLKNET", F36)), ISNUMBER(SEARCH("TESTE", F36))), "6.1 Despesas Administrativas (Gerais)", IFERROR(VLOOKUP(H36, De_Para!A:B, 2, FALSE), "NÃO MAPEADO"))), IFERROR(VLOOKUP(H36, De_Para!A:B, 2, FALSE), "NÃO MAPEADO"))
A37: 69662 | B37: Sicredi SNI | C37: 30/06/2026 | D37: 30/06/2026 | E37: Dinheiro | F37: Boleto "66667" do cliente "LAURINDA DAS DORES IZIDORO" | G37: system | H37: 01.01.01 : Mensalidade | I37: 104.9 | K37: =IF(H37="02.09 : Outras Saídas", IF(OR(ISNUMBER(SEARCH("CHEQUE COMPE SICREDI", F37)), ISNUMBER(SEARCH("aniversario", F37)), ISNUMBER(SEARCH("churrasco", F37)), ISNUMBER(SEARCH("bolo", F37)), ISNUMBER(SEARCH("SUPERMERCADO", F37))), "6.1 Despesas Administrativas (Pessoal)", IF(OR(ISNUMBER(SEARCH("DLKNET", F37)), ISNUMBER(SEARCH("TESTE", F37))), "6.1 Despesas Administrativas (Gerais)", IFERROR(VLOOKUP(H37, De_Para!A:B, 2, FALSE), "NÃO MAPEADO"))), IFERROR(VLOOKUP(H37, De_Para!A:B, 2, FALSE), "NÃO MAPEADO"))
A38: 69661 | B38: Sicredi SNI | C38: 30/06/2026 | D38: 30/06/2026 | E38: PIX | F38: Boleto "63097" do cliente "MARIA APARECIDA BREKE BONDARYK" | G38: system | H38: 02.03.02.01 : Cobrança Bancaria | J38: -0.49 | K38: =IF(H38="02.09 : Outras Saídas", IF(OR(ISNUMBER(SEARCH("CHEQUE COMPE SICREDI", F38)), ISNUMBER(SEARCH("aniversario", F38)), ISNUMBER(SEARCH("churrasco", F38)), ISNUMBER(SEARCH("bolo", F38)), ISNUMBER(SEARCH("SUPERMERCADO", F38))), "6.1 Despesas Administrativas (Pessoal)", IF(OR(ISNUMBER(SEARCH("DLKNET", F38)), ISNUMBER(SEARCH("TESTE", F38))), "6.1 Despesas Administrativas (Gerais)", IFERROR(VLOOKUP(H38, De_Para!A:B, 2, FALSE), "NÃO MAPEADO"))), IFERROR(VLOOKUP(H38, De_Para!A:B, 2, FALSE), "NÃO MAPEADO"))
A39: 69660 | B39: Sicredi SNI | C39: 30/06/2026 | D39: 30/06/2026 | E39: PIX | F39: Boleto "63097" do cliente "MARIA APARECIDA BREKE BONDARYK" | G39: system | H39: 01.01.01 : Mensalidade | I39: 104.9 | K39: =IF(H39="02.09 : Outras Saídas", IF(OR(ISNUMBER(SEARCH("CHEQUE COMPE SICREDI", F39)), ISNUMBER(SEARCH("aniversario", F39)), ISNUMBER(SEARCH("churrasco", F39)), ISNUMBER(SEARCH("bolo", F39)), ISNUMBER(SEARCH("SUPERMERCADO", F39))), "6.1 Despesas Administrativas (Pessoal)", IF(OR(ISNUMBER(SEARCH("DLKNET", F39)), ISNUMBER(SEARCH("TESTE", F39))), "6.1 Despesas Administrativas (Gerais)", IFERROR(VLOOKUP(H39, De_Para!A:B, 2, FALSE), "NÃO MAPEADO"))), IFERROR(VLOOKUP(H39, De_Para!A:B, 2, FALSE), "NÃO MAPEADO"))
A40: 69659 | B40: Sicoob | C40: 30/06/2026 | D40: 30/06/2026 | E40: Dinheiro | F40: Boleto "57569" do cliente "MARIA LÚCIA BATISTA DOS REIS" | G40: system | H40: 02.03.02.01 : Cobrança Bancaria | J40: -0.88 | K40: =IF(H40="02.09 : Outras Saídas", IF(OR(ISNUMBER(SEARCH("CHEQUE COMPE SICREDI", F40)), ISNUMBER(SEARCH("aniversario", F40)), ISNUMBER(SEARCH("churrasco", F40)), ISNUMBER(SEARCH("bolo", F40)), ISNUMBER(SEARCH("SUPERMERCADO", F40))), "6.1 Despesas Administrativas (Pessoal)", IF(OR(ISNUMBER(SEARCH("DLKNET", F40)), ISNUMBER(SEARCH("TESTE", F40))), "6.1 Despesas Administrativas (Gerais)", IFERROR(VLOOKUP(H40, De_Para!A:B, 2, FALSE), "NÃO MAPEADO"))), IFERROR(VLOOKUP(H40, De_Para!A:B, 2, FALSE), "NÃO MAPEADO"))
A41: 69658 | B41: Sicoob | C41: 30/06/2026 | D41: 30/06/2026 | E41: Dinheiro | F41: Boleto "57569" do cliente "MARIA LÚCIA BATISTA DOS REIS" | G41: system | H41: 01.01.01 : Mensalidade | I41: 80 | K41: =IF(H41="02.09 : Outras Saídas", IF(OR(ISNUMBER(SEARCH("CHEQUE COMPE SICREDI", F41)), ISNUMBER(SEARCH("aniversario", F41)), ISNUMBER(SEARCH("churrasco", F41)), ISNUMBER(SEARCH("bolo", F41)), ISNUMBER(SEARCH("SUPERMERCADO", F41))), "6.1 Despesas Administrativas (Pessoal)", IF(OR(ISNUMBER(SEARCH("DLKNET", F41)), ISNUMBER(SEARCH("TESTE", F41))), "6.1 Despesas Administrativas (Gerais)", IFERROR(VLOOKUP(H41, De_Para!A:B, 2, FALSE), "NÃO MAPEADO"))), IFERROR(VLOOKUP(H41, De_Para!A:B, 2, FALSE), "NÃO MAPEADO"))
A42: 69657 | B42: Sicoob | C42: 30/06/2026 | D42: 30/06/2026 | E42: Dinheiro | F42: Boleto "57371" do cliente "SEBASTIAO DONIZETE DE FARIA" | G42: system | H42: 02.03.02.01 : Cobrança Bancaria | J42: -0.88 | K42: =IF(H42="02.09 : Outras Saídas", IF(OR(ISNUMBER(SEARCH("CHEQUE COMPE SICREDI", F42)), ISNUMBER(SEARCH("aniversario", F42)), ISNUMBER(SEARCH("churrasco", F42)), ISNUMBER(SEARCH("bolo", F42)), ISNUMBER(SEARCH("SUPERMERCADO", F42))), "6.1 Despesas Administrativas (Pessoal)", IF(OR(ISNUMBER(SEARCH("DLKNET", F42)), ISNUMBER(SEARCH("TESTE", F42))), "6.1 Despesas Administrativas (Gerais)", IFERROR(VLOOKUP(H42, De_Para!A:B, 2, FALSE), "NÃO MAPEADO"))), IFERROR(VLOOKUP(H42, De_Para!A:B, 2, FALSE), "NÃO MAPEADO"))
A43: 69656 | B43: Sicoob | C43: 30/06/2026 | D43: 30/06/2026 | E43: Dinheiro | F43: Boleto "57371" do cliente "SEBASTIAO DONIZETE DE FARIA" | G43: system | H43: 01.01.01 : Mensalidade | I43: 105 | K43: =IF(H43="02.09 : Outras Saídas", IF(OR(ISNUMBER(SEARCH("CHEQUE COMPE SICREDI", F43)), ISNUMBER(SEARCH("aniversario", F43)), ISNUMBER(SEARCH("churrasco", F43)), ISNUMBER(SEARCH("bolo", F43)), ISNUMBER(SEARCH("SUPERMERCADO", F43))), "6.1 Despesas Administrativas (Pessoal)", IF(OR(ISNUMBER(SEARCH("DLKNET", F43)), ISNUMBER(SEARCH("TESTE", F43))), "6.1 Despesas Administrativas (Gerais)", IFERROR(VLOOKUP(H43, De_Para!A:B, 2, FALSE), "NÃO MAPEADO"))), IFERROR(VLOOKUP(H43, De_Para!A:B, 2, FALSE), "NÃO MAPEADO"))
A44: 69655 | B44: Sicoob | C44: 30/06/2026 | D44: 30/06/2026 | E44: Dinheiro | F44: Boleto "67854" do cliente "NEUZA FERNANDES" | G44: system | H44: 02.03.02.01 : Cobrança Bancaria | J44: -0.88 | K44: =IF(H44="02.09 : Outras Saídas", IF(OR(ISNUMBER(SEARCH("CHEQUE COMPE SICREDI", F44)), ISNUMBER(SEARCH("aniversario", F44)), ISNUMBER(SEARCH("churrasco", F44)), ISNUMBER(SEARCH("bolo", F44)), ISNUMBER(SEARCH("SUPERMERCADO", F44))), "6.1 Despesas Administrativas (Pessoal)", IF(OR(ISNUMBER(SEARCH("DLKNET", F44)), ISNUMBER(SEARCH("TESTE", F44))), "6.1 Despesas Administrativas (Gerais)", IFERROR(VLOOKUP(H44, De_Para!A:B, 2, FALSE), "NÃO MAPEADO"))), IFERROR(VLOOKUP(H44, De_Para!A:B, 2, FALSE), "NÃO MAPEADO"))
A45: 69654 | B45: Sicoob | C45: 30/06/2026 | D45: 30/06/2026 | E45: Dinheiro | F45: Boleto "67854" do cliente "NEUZA FERNANDES" | G45: system | H45: 01.01.01 : Mensalidade | I45: 104.9 | K45: =IF(H45="02.09 : Outras Saídas", IF(OR(ISNUMBER(SEARCH("CHEQUE COMPE SICREDI", F45)), ISNUMBER(SEARCH("aniversario", F45)), ISNUMBER(SEARCH("churrasco", F45)), ISNUMBER(SEARCH("bolo", F45)), ISNUMBER(SEARCH("SUPERMERCADO", F45))), "6.1 Despesas Administrativas (Pessoal)", IF(OR(ISNUMBER(SEARCH("DLKNET", F45)), ISNUMBER(SEARCH("TESTE", F45))), "6.1 Despesas Administrativas (Gerais)", IFERROR(VLOOKUP(H45, De_Para!A:B, 2, FALSE), "NÃO MAPEADO"))), IFERROR(VLOOKUP(H45, De_Para!A:B, 2, FALSE), "NÃO MAPEADO"))
A46: 69653 | B46: Sicredi SNI | C46: 30/06/2026 | D46: 30/06/2026 | E46: PIX | F46: Boleto "72786" do cliente "VALDECIR APARECIDO DA SILVA" | G46: system | H46: 02.03.02.01 : Cobrança Bancaria | J46: -0.49 | K46: =IF(H46="02.09 : Outras Saídas", IF(OR(ISNUMBER(SEARCH("CHEQUE COMPE SICREDI", F46)), ISNUMBER(SEARCH("aniversario", F46)), ISNUMBER(SEARCH("churrasco", F46)), ISNUMBER(SEARCH("bolo", F46)), ISNUMBER(SEARCH("SUPERMERCADO", F46))), "6.1 Despesas Administrativas (Pessoal)", IF(OR(ISNUMBER(SEARCH("DLKNET", F46)), ISNUMBER(SEARCH("TESTE", F46))), "6.1 Despesas Administrativas (Gerais)", IFERROR(VLOOKUP(H46, De_Para!A:B, 2, FALSE), "NÃO MAPEADO"))), IFERROR(VLOOKUP(H46, De_Para!A:B, 2, FALSE), "NÃO MAPEADO"))
A47: 69652 | B47: Sicredi SNI | C47: 30/06/2026 | D47: 30/06/2026 | E47: PIX | F47: Boleto "72786" do cliente "VALDECIR APARECIDO DA SILVA" | G47: system | H47: 01.01.01 : Mensalidade | I47: 40.33 | K47: =IF(H47="02.09 : Outras Saídas", IF(OR(ISNUMBER(SEARCH("CHEQUE COMPE SICREDI", F47)), ISNUMBER(SEARCH("aniversario", F47)), ISNUMBER(SEARCH("churrasco", F47)), ISNUMBER(SEARCH("bolo", F47)), ISNUMBER(SEARCH("SUPERMERCADO", F47))), "6.1 Despesas Administrativas (Pessoal)", IF(OR(ISNUMBER(SEARCH("DLKNET", F47)), ISNUMBER(SEARCH("TESTE", F47))), "6.1 Despesas Administrativas (Gerais)", IFERROR(VLOOKUP(H47, De_Para!A:B, 2, FALSE), "NÃO MAPEADO"))), IFERROR(VLOOKUP(H47, De_Para!A:B, 2, FALSE), "NÃO MAPEADO"))
A48: 69651 | B48: Sicredi SNI | C48: 30/06/2026 | D48: 30/06/2026 | E48: PIX | F48: Boleto "60121" do cliente "LUIZ CARLOS DA SILVA" | G48: system | H48: 02.03.02.01 : Cobrança Bancaria | J48: -0.49 | K48: =IF(H48="02.09 : Outras Saídas", IF(OR(ISNUMBER(SEARCH("CHEQUE COMPE SICREDI", F48)), ISNUMBER(SEARCH("aniversario", F48)), ISNUMBER(SEARCH("churrasco", F48)), ISNUMBER(SEARCH("bolo", F48)), ISNUMBER(SEARCH("SUPERMERCADO", F48))), "6.1 Despesas Administrativas (Pessoal)", IF(OR(ISNUMBER(SEARCH("DLKNET", F48)), ISNUMBER(SEARCH("TESTE", F48))), "6.1 Despesas Administrativas (Gerais)", IFERROR(VLOOKUP(H48, De_Para!A:B, 2, FALSE), "NÃO MAPEADO"))), IFERROR(VLOOKUP(H48, De_Para!A:B, 2, FALSE), "NÃO MAPEADO"))
A49: 69650 | B49: Sicredi SNI | C49: 30/06/2026 | D49: 30/06/2026 | E49: PIX | F49: Boleto "60121" do cliente "LUIZ CARLOS DA SILVA" | G49: system | H49: 01.01.01 : Mensalidade | I49: 105 | K49: =IF(H49="02.09 : Outras Saídas", IF(OR(ISNUMBER(SEARCH("CHEQUE COMPE SICREDI", F49)), ISNUMBER(SEARCH("aniversario", F49)), ISNUMBER(SEARCH("churrasco", F49)), ISNUMBER(SEARCH("bolo", F49)), ISNUMBER(SEARCH("SUPERMERCADO", F49))), "6.1 Despesas Administrativas (Pessoal)", IF(OR(ISNUMBER(SEARCH("DLKNET", F49)), ISNUMBER(SEARCH("TESTE", F49))), "6.1 Despesas Administrativas (Gerais)", IFERROR(VLOOKUP(H49, De_Para!A:B, 2, FALSE), "NÃO MAPEADO"))), IFERROR(VLOOKUP(H49, De_Para!A:B, 2, FALSE), "NÃO MAPEADO"))
A50: 69649 | B50: Sicredi SNI | C50: 30/06/2026 | D50: 30/06/2026 | E50: Dinheiro | F50: Boleto "61504" do cliente "DEJAIME VITORINO DE SOUZA" | G50: system | H50: 02.03.02.01 : Cobrança Bancaria | J50: -1.08 | K50: =IF(H50="02.09 : Outras Saídas", IF(OR(ISNUMBER(SEARCH("CHEQUE COMPE SICREDI", F50)), ISNUMBER(SEARCH("aniversario", F50)), ISNUMBER(SEARCH("churrasco", F50)), ISNUMBER(SEARCH("bolo", F50)), ISNUMBER(SEARCH("SUPERMERCADO", F50))), "6.1 Despesas Administrativas (Pessoal)", IF(OR(ISNUMBER(SEARCH("DLKNET", F50)), ISNUMBER(SEARCH("TESTE", F50))), "6.1 Despesas Administrativas (Gerais)", IFERROR(VLOOKUP(H50, De_Para!A:B, 2, FALSE), "NÃO MAPEADO"))), IFERROR(VLOOKUP(H50, De_Para!A:B, 2, FALSE), "NÃO MAPEADO"))
A51: 69648 | B51: Sicredi SNI | C51: 30/06/2026 | D51: 30/06/2026 | E51: Dinheiro | F51: Boleto "61504" do cliente "DEJAIME VITORINO DE SOUZA" | G51: system | H51: 01.01.01 : Mensalidade | I51: 105 | K51: =IF(H51="02.09 : Outras Saídas", IF(OR(ISNUMBER(SEARCH("CHEQUE COMPE SICREDI", F51)), ISNUMBER(SEARCH("aniversario", F51)), ISNUMBER(SEARCH("churrasco", F51)), ISNUMBER(SEARCH("bolo", F51)), ISNUMBER(SEARCH("SUPERMERCADO", F51))), "6.1 Despesas Administrativas (Pessoal)", IF(OR(ISNUMBER(SEARCH("DLKNET", F51)), ISNUMBER(SEARCH("TESTE", F51))), "6.1 Despesas Administrativas (Gerais)", IFERROR(VLOOKUP(H51, De_Para!A:B, 2, FALSE), "NÃO MAPEADO"))), IFERROR(VLOOKUP(H51, De_Para!A:B, 2, FALSE), "NÃO MAPEADO"))
A52: 69647 | B52: Sicredi SNI | C52: 30/06/2026 | D52: 30/06/2026 | E52: Dinheiro | F52: Boleto "61011" do cliente "RONALDO CAMILO MESSIAS" | G52: system | H52: 02.03.02.01 : Cobrança Bancaria | J52: -1.08 | K52: =IF(H52="02.09 : Outras Saídas", IF(OR(ISNUMBER(SEARCH("CHEQUE COMPE SICREDI", F52)), ISNUMBER(SEARCH("aniversario", F52)), ISNUMBER(SEARCH("churrasco", F52)), ISNUMBER(SEARCH("bolo", F52)), ISNUMBER(SEARCH("SUPERMERCADO", F52))), "6.1 Despesas Administrativas (Pessoal)", IF(OR(ISNUMBER(SEARCH("DLKNET", F52)), ISNUMBER(SEARCH("TESTE", F52))), "6.1 Despesas Administrativas (Gerais)", IFERROR(VLOOKUP(H52, De_Para!A:B, 2, FALSE), "NÃO MAPEADO"))), IFERROR(VLOOKUP(H52, De_Para!A:B, 2, FALSE), "NÃO MAPEADO"))
A53: 69646 | B53: Sicredi SNI | C53: 30/06/2026 | D53: 30/06/2026 | E53: Dinheiro | F53: Boleto "61011" do cliente "RONALDO CAMILO MESSIAS" | G53: system | H53: 01.01.01 : Mensalidade | I53: 107.25 | K53: =IF(H53="02.09 : Outras Saídas", IF(OR(ISNUMBER(SEARCH("CHEQUE COMPE SICREDI", F53)), ISNUMBER(SEARCH("aniversario", F53)), ISNUMBER(SEARCH("churrasco", F53)), ISNUMBER(SEARCH("bolo", F53)), ISNUMBER(SEARCH("SUPERMERCADO", F53))), "6.1 Despesas Administrativas (Pessoal)", IF(OR(ISNUMBER(SEARCH("DLKNET", F53)), ISNUMBER(SEARCH("TESTE", F53))), "6.1 Despesas Administrativas (Gerais)", IFERROR(VLOOKUP(H53, De_Para!A:B, 2, FALSE), "NÃO MAPEADO"))), IFERROR(VLOOKUP(H53, De_Para!A:B, 2, FALSE), "NÃO MAPEADO"))
A54: 69645 | B54: Sicredi SNI | C54: 30/06/2026 | D54: 30/06/2026 | E54: Dinheiro | F54: Boleto "55343" do cliente "REINALDO RAMOS DE ALMEIDA" | G54: system | H54: 02.03.02.01 : Cobrança Bancaria | J54: -1.08 | K54: =IF(H54="02.09 : Outras Saídas", IF(OR(ISNUMBER(SEARCH("CHEQUE COMPE SICREDI", F54)), ISNUMBER(SEARCH("aniversario", F54)), ISNUMBER(SEARCH("churrasco", F54)), ISNUMBER(SEARCH("bolo", F54)), ISNUMBER(SEARCH("SUPERMERCADO", F54))), "6.1 Despesas Administrativas (Pessoal)", IF(OR(ISNUMBER(SEARCH("DLKNET", F54)), ISNUMBER(SEARCH("TESTE", F54))), "6.1 Despesas Administrativas (Gerais)", IFERROR(VLOOKUP(H54, De_Para!A:B, 2, FALSE), "NÃO MAPEADO"))), IFERROR(VLOOKUP(H54, De_Para!A:B, 2, FALSE), "NÃO MAPEADO"))
A55: 69644 | B55: Sicredi SNI | C55: 30/06/2026 | D55: 30/06/2026 | E55: Dinheiro | F55: Boleto "55343" do cliente "REINALDO RAMOS DE ALMEIDA" | G55: system | H55: 01.01.01 : Mensalidade | I55: 84 | K55: =IF(H55="02.09 : Outras Saídas", IF(OR(ISNUMBER(SEARCH("CHEQUE COMPE SICREDI", F55)), ISNUMBER(SEARCH("aniversario", F55)), ISNUMBER(SEARCH("churrasco", F55)), ISNUMBER(SEARCH("bolo", F55)), ISNUMBER(SEARCH("SUPERMERCADO", F55))), "6.1 Despesas Administrativas (Pessoal)", IF(OR(ISNUMBER(SEARCH("DLKNET", F55)), ISNUMBER(SEARCH("TESTE", F55))), "6.1 Despesas Administrativas (Gerais)", IFERROR(VLOOKUP(H55, De_Para!A:B, 2, FALSE), "NÃO MAPEADO"))), IFERROR(VLOOKUP(H55, De_Para!A:B, 2, FALSE), "NÃO MAPEADO"))
A56: 69643 | B56: Sicredi SNI | C56: 30/06/2026 | D56: 30/06/2026 | E56: Dinheiro | F56: Boleto "55288" do cliente "ROSIMERE MARTINS DIOGO" | G56: system | H56: 02.03.02.01 : Cobrança Bancaria | J56: -1.08 | K56: =IF(H56="02.09 : Outras Saídas", IF(OR(ISNUMBER(SEARCH("CHEQUE COMPE SICREDI", F56)), ISNUMBER(SEARCH("aniversario", F56)), ISNUMBER(SEARCH("churrasco", F56)), ISNUMBER(SEARCH("bolo", F56)), ISNUMBER(SEARCH("SUPERMERCADO", F56))), "6.1 Despesas Administrativas (Pessoal)", IF(OR(ISNUMBER(SEARCH("DLKNET", F56)), ISNUMBER(SEARCH("TESTE", F56))), "6.1 Despesas Administrativas (Gerais)", IFERROR(VLOOKUP(H56, De_Para!A:B, 2, FALSE), "NÃO MAPEADO"))), IFERROR(VLOOKUP(H56, De_Para!A:B, 2, FALSE), "NÃO MAPEADO"))
A57: 69642 | B57: Sicredi SNI | C57: 30/06/2026 | D57: 30/06/2026 | E57: Dinheiro | F57: Boleto "55288" do cliente "ROSIMERE MARTINS DIOGO" | G57: system | H57: 01.01.01 : Mensalidade | I57: 102.3 | K57: =IF(H57="02.09 : Outras Saídas", IF(OR(ISNUMBER(SEARCH("CHEQUE COMPE SICREDI", F57)), ISNUMBER(SEARCH("aniversario", F57)), ISNUMBER(SEARCH("churrasco", F57)), ISNUMBER(SEARCH("bolo", F57)), ISNUMBER(SEARCH("SUPERMERCADO", F57))), "6.1 Despesas Administrativas (Pessoal)", IF(OR(ISNUMBER(SEARCH("DLKNET", F57)), ISNUMBER(SEARCH("TESTE", F57))), "6.1 Despesas Administrativas (Gerais)", IFERROR(VLOOKUP(H57, De_Para!A:B, 2, FALSE), "NÃO MAPEADO"))), IFERROR(VLOOKUP(H57, De_Para!A:B, 2, FALSE), "NÃO MAPEADO"))
A58: 69641 | B58: Sicoob | C58: 30/06/2026 | D58: 30/06/2026 | E58: Dinheiro | F58: Boleto "59567" do cliente "NOEMI PEREIRA ALVES BARBOSA" | G58: system | H58: 02.03.02.01 : Cobrança Bancaria | J58: -0.88 | K58: =IF(H58="02.09 : Outras Saídas", IF(OR(ISNUMBER(SEARCH("CHEQUE COMPE SICREDI", F58)), ISNUMBER(SEARCH("aniversario", F58)), ISNUMBER(SEARCH("churrasco", F58)), ISNUMBER(SEARCH("bolo", F58)), ISNUMBER(SEARCH("SUPERMERCADO", F58))), "6.1 Despesas Administrativas (Pessoal)", IF(OR(ISNUMBER(SEARCH("DLKNET", F58)), ISNUMBER(SEARCH("TESTE", F58))), "6.1 Despesas Administrativas (Gerais)", IFERROR(VLOOKUP(H58, De_Para!A:B, 2, FALSE), "NÃO MAPEADO"))), IFERROR(VLOOKUP(H58, De_Para!A:B, 2, FALSE), "NÃO MAPEADO"))
A59: 69640 | B59: Sicoob | C59: 30/06/2026 | D59: 30/06/2026 | E59: Dinheiro | F59: Boleto "59567" do cliente "NOEMI PEREIRA ALVES BARBOSA" | G59: system | H59: 01.01.01 : Mensalidade | I59: 105 | K59: =IF(H59="02.09 : Outras Saídas", IF(OR(ISNUMBER(SEARCH("CHEQUE COMPE SICREDI", F59)), ISNUMBER(SEARCH("aniversario", F59)), ISNUMBER(SEARCH("churrasco", F59)), ISNUMBER(SEARCH("bolo", F59)), ISNUMBER(SEARCH("SUPERMERCADO", F59))), "6.1 Despesas Administrativas (Pessoal)", IF(OR(ISNUMBER(SEARCH("DLKNET", F59)), ISNUMBER(SEARCH("TESTE", F59))), "6.1 Despesas Administrativas (Gerais)", IFERROR(VLOOKUP(H59, De_Para!A:B, 2, FALSE), "NÃO MAPEADO"))), IFERROR(VLOOKUP(H59, De_Para!A:B, 2, FALSE), "NÃO MAPEADO"))
A60: 69639 | B60: Sicoob | C60: 30/06/2026 | D60: 30/06/2026 | E60: Dinheiro | F60: Boleto "59409" do cliente "EDINA PAULA FRANÇA" | G60: system | H60: 02.03.02.01 : Cobrança Bancaria | J60: -0.88 | K60: =IF(H60="02.09 : Outras Saídas", IF(OR(ISNUMBER(SEARCH("CHEQUE COMPE SICREDI", F60)), ISNUMBER(SEARCH("aniversario", F60)), ISNUMBER(SEARCH("churrasco", F60)), ISNUMBER(SEARCH("bolo", F60)), ISNUMBER(SEARCH("SUPERMERCADO", F60))), "6.1 Despesas Administrativas (Pessoal)", IF(OR(ISNUMBER(SEARCH("DLKNET", F60)), ISNUMBER(SEARCH("TESTE", F60))), "6.1 Despesas Administrativas (Gerais)", IFERROR(VLOOKUP(H60, De_Para!A:B, 2, FALSE), "NÃO MAPEADO"))), IFERROR(VLOOKUP(H60, De_Para!A:B, 2, FALSE), "NÃO MAPEADO"))
A61: 69638 | B61: Sicoob | C61: 30/06/2026 | D61: 30/06/2026 | E61: Dinheiro | F61: Boleto "59409" do cliente "EDINA PAULA FRANÇA" | G61: system | H61: 01.01.01 : Mensalidade | I61: 110 | K61: =IF(H61="02.09 : Outras Saídas", IF(OR(ISNUMBER(SEARCH("CHEQUE COMPE SICREDI", F61)), ISNUMBER(SEARCH("aniversario", F61)), ISNUMBER(SEARCH("churrasco", F61)), ISNUMBER(SEARCH("bolo", F61)), ISNUMBER(SEARCH("SUPERMERCADO", F61))), "6.1 Despesas Administrativas (Pessoal)", IF(OR(ISNUMBER(SEARCH("DLKNET", F61)), ISNUMBER(SEARCH("TESTE", F61))), "6.1 Despesas Administrativas (Gerais)", IFERROR(VLOOKUP(H61, De_Para!A:B, 2, FALSE), "NÃO MAPEADO"))), IFERROR(VLOOKUP(H61, De_Para!A:B, 2, FALSE), "NÃO MAPEADO"))
A62: 69637 | B62: Sicoob | C62: 30/06/2026 | D62: 30/06/2026 | E62: Dinheiro | F62: Boleto "55190" do cliente "ADRIANE INOCENCIA DA SLVA OLIVEIRA" | G62: system | H62: 02.03.02.01 : Cobrança Bancaria | J62: -0.88 | K62: =IF(H62="02.09 : Outras Saídas", IF(OR(ISNUMBER(SEARCH("CHEQUE COMPE SICREDI", F62)), ISNUMBER(SEARCH("aniversario", F62)), ISNUMBER(SEARCH("churrasco", F62)), ISNUMBER(SEARCH("bolo", F62)), ISNUMBER(SEARCH("SUPERMERCADO", F62))), "6.1 Despesas Administrativas (Pessoal)", IF(OR(ISNUMBER(SEARCH("DLKNET", F62)), ISNUMBER(SEARCH("TESTE", F62))), "6.1 Despesas Administrativas (Gerais)", IFERROR(VLOOKUP(H62, De_Para!A:B, 2, FALSE), "NÃO MAPEADO"))), IFERROR(VLOOKUP(H62, De_Para!A:B, 2, FALSE), "NÃO MAPEADO"))
A63: 69636 | B63: Sicoob | C63: 30/06/2026 | D63: 30/06/2026 | E63: Dinheiro | F63: Boleto "55190" do cliente "ADRIANE INOCENCIA DA SLVA OLIVEIRA" | G63: system | H63: 01.01.01 : Mensalidade | I63: 105 | K63: =IF(H63="02.09 : Outras Saídas", IF(OR(ISNUMBER(SEARCH("CHEQUE COMPE SICREDI", F63)), ISNUMBER(SEARCH("aniversario", F63)), ISNUMBER(SEARCH("churrasco", F63)), ISNUMBER(SEARCH("bolo", F63)), ISNUMBER(SEARCH("SUPERMERCADO", F63))), "6.1 Despesas Administrativas (Pessoal)", IF(OR(ISNUMBER(SEARCH("DLKNET", F63)), ISNUMBER(SEARCH("TESTE", F63))), "6.1 Despesas Administrativas (Gerais)", IFERROR(VLOOKUP(H63, De_Para!A:B, 2, FALSE), "NÃO MAPEADO"))), IFERROR(VLOOKUP(H63, De_Para!A:B, 2, FALSE), "NÃO MAPEADO"))
A64: 69635 | B64: Sicoob | C64: 30/06/2026 | D64: 30/06/2026 | E64: Dinheiro | F64: Boleto "55179" do cliente "TIAGO DA CUNHA PINTO" | G64: system | H64: 02.03.02.01 : Cobrança Bancaria | J64: -0.88 | K64: =IF(H64="02.09 : Outras Saídas", IF(OR(ISNUMBER(SEARCH("CHEQUE COMPE SICREDI", F64)), ISNUMBER(SEARCH("aniversario", F64)), ISNUMBER(SEARCH("churrasco", F64)), ISNUMBER(SEARCH("bolo", F64)), ISNUMBER(SEARCH("SUPERMERCADO", F64))), "6.1 Despesas Administrativas (Pessoal)", IF(OR(ISNUMBER(SEARCH("DLKNET", F64)), ISNUMBER(SEARCH("TESTE", F64))), "6.1 Despesas Administrativas (Gerais)", IFERROR(VLOOKUP(H64, De_Para!A:B, 2, FALSE), "NÃO MAPEADO"))), IFERROR(VLOOKUP(H64, De_Para!A:B, 2, FALSE), "NÃO MAPEADO"))
A65: 69634 | B65: Sicoob | C65: 30/06/2026 | D65: 30/06/2026 | E65: Dinheiro | F65: Boleto "55179" do cliente "TIAGO DA CUNHA PINTO" | G65: system | H65: 01.01.01 : Mensalidade | I65: 105 | K65: =IF(H65="02.09 : Outras Saídas", IF(OR(ISNUMBER(SEARCH("CHEQUE COMPE SICREDI", F65)), ISNUMBER(SEARCH("aniversario", F65)), ISNUMBER(SEARCH("churrasco", F65)), ISNUMBER(SEARCH("bolo", F65)), ISNUMBER(SEARCH("SUPERMERCADO", F65))), "6.1 Despesas Administrativas (Pessoal)", IF(OR(ISNUMBER(SEARCH("DLKNET", F65)), ISNUMBER(SEARCH("TESTE", F65))), "6.1 Despesas Administrativas (Gerais)", IFERROR(VLOOKUP(H65, De_Para!A:B, 2, FALSE), "NÃO MAPEADO"))), IFERROR(VLOOKUP(H65, De_Para!A:B, 2, FALSE), "NÃO MAPEADO"))
A66: 69633 | B66: Sicredi SNI | C66: 30/06/2026 | D66: 30/06/2026 | E66: PIX | F66: Boleto "61423" do cliente "REINALDO APARECIDO DE LIMA" | G66: system | H66: 02.03.02.01 : Cobrança Bancaria | J66: -0.49 | K66: =IF(H66="02.09 : Outras Saídas", IF(OR(ISNUMBER(SEARCH("CHEQUE COMPE SICREDI", F66)), ISNUMBER(SEARCH("aniversario", F66)), ISNUMBER(SEARCH("churrasco", F66)), ISNUMBER(SEARCH("bolo", F66)), ISNUMBER(SEARCH("SUPERMERCADO", F66))), "6.1 Despesas Administrativas (Pessoal)", IF(OR(ISNUMBER(SEARCH("DLKNET", F66)), ISNUMBER(SEARCH("TESTE", F66))), "6.1 Despesas Administrativas (Gerais)", IFERROR(VLOOKUP(H66, De_Para!A:B, 2, FALSE), "NÃO MAPEADO"))), IFERROR(VLOOKUP(H66, De_Para!A:B, 2, FALSE), "NÃO MAPEADO"))
A67: 69632 | B67: Sicredi SNI | C67: 30/06/2026 | D67: 30/06/2026 | E67: PIX | F67: Boleto "61423" do cliente "REINALDO APARECIDO DE LIMA" | G67: system | H67: 01.01.01 : Mensalidade | I67: 105 | K67: =IF(H67="02.09 : Outras Saídas", IF(OR(ISNUMBER(SEARCH("CHEQUE COMPE SICREDI", F67)), ISNUMBER(SEARCH("aniversario", F67)), ISNUMBER(SEARCH("churrasco", F67)), ISNUMBER(SEARCH("bolo", F67)), ISNUMBER(SEARCH("SUPERMERCADO", F67))), "6.1 Despesas Administrativas (Pessoal)", IF(OR(ISNUMBER(SEARCH("DLKNET", F67)), ISNUMBER(SEARCH("TESTE", F67))), "6.1 Despesas Administrativas (Gerais)", IFERROR(VLOOKUP(H67, De_Para!A:B, 2, FALSE), "NÃO MAPEADO"))), IFERROR(VLOOKUP(H67, De_Para!A:B, 2, FALSE), "NÃO MAPEADO"))
A68: 69631 | B68: Sicoob | C68: 30/06/2026 | D68: 29/06/2026 | E68: Dinheiro | F68: Boleto "63558" do cliente "MARIA EDUARDA SILVA DUTRA" | G68: system | H68: 02.03.02.01 : Cobrança Bancaria | J68: -0.88 | K68: =IF(H68="02.09 : Outras Saídas", IF(OR(ISNUMBER(SEARCH("CHEQUE COMPE SICREDI", F68)), ISNUMBER(SEARCH("aniversario", F68)), ISNUMBER(SEARCH("churrasco", F68)), ISNUMBER(SEARCH("bolo", F68)), ISNUMBER(SEARCH("SUPERMERCADO", F68))), "6.1 Despesas Administrativas (Pessoal)", IF(OR(ISNUMBER(SEARCH("DLKNET", F68)), ISNUMBER(SEARCH("TESTE", F68))), "6.1 Despesas Administrativas (Gerais)", IFERROR(VLOOKUP(H68, De_Para!A:B, 2, FALSE), "NÃO MAPEADO"))), IFERROR(VLOOKUP(H68, De_Para!A:B, 2, FALSE), "NÃO MAPEADO"))
A69: 69630 | B69: Sicoob | C69: 30/06/2026 | D69: 29/06/2026 | E69: Dinheiro | F69: Boleto "63558" do cliente "MARIA EDUARDA SILVA DUTRA" | G69: system | H69: 01.01.01 : Mensalidade | I69: 104.9 | K69: =IF(H69="02.09 : Outras Saídas", IF(OR(ISNUMBER(SEARCH("CHEQUE COMPE SICREDI", F69)), ISNUMBER(SEARCH("aniversario", F69)), ISNUMBER(SEARCH("churrasco", F69)), ISNUMBER(SEARCH("bolo", F69)), ISNUMBER(SEARCH("SUPERMERCADO", F69))), "6.1 Despesas Administrativas (Pessoal)", IF(OR(ISNUMBER(SEARCH("DLKNET", F69)), ISNUMBER(SEARCH("TESTE", F69))), "6.1 Despesas Administrativas (Gerais)", IFERROR(VLOOKUP(H69, De_Para!A:B, 2, FALSE), "NÃO MAPEADO"))), IFERROR(VLOOKUP(H69, De_Para!A:B, 2, FALSE), "NÃO MAPEADO"))
A70: 69629 | B70: Sicredi SNI | C70: 29/06/2026 | D70: 29/06/2026 | E70: PIX | F70: Boleto "67741" do cliente "JANDIRA APARECIDA DE LIMA LEAL" | G70: system | H70: 02.03.02.01 : Cobrança Bancaria | J70: -0.49 | K70: =IF(H70="02.09 : Outras Saídas", IF(OR(ISNUMBER(SEARCH("CHEQUE COMPE SICREDI", F70)), ISNUMBER(SEARCH("aniversario", F70)), ISNUMBER(SEARCH("churrasco", F70)), ISNUMBER(SEARCH("bolo", F70)), ISNUMBER(SEARCH("SUPERMERCADO", F70))), "6.1 Despesas Administrativas (Pessoal)", IF(OR(ISNUMBER(SEARCH("DLKNET", F70)), ISNUMBER(SEARCH("TESTE", F70))), "6.1 Despesas Administrativas (Gerais)", IFERROR(VLOOKUP(H70, De_Para!A:B, 2, FALSE), "NÃO MAPEADO"))), IFERROR(VLOOKUP(H70, De_Para!A:B, 2, FALSE), "NÃO MAPEADO"))
A71: 69628 | B71: Sicredi SNI | C71: 29/06/2026 | D71: 29/06/2026 | E71: PIX | F71: Boleto "67741" do cliente "JANDIRA APARECIDA DE LIMA LEAL" | G71: system | H71: 01.03.01 : Mensalidade | I71: 107.42 | K71: =IF(H71="02.09 : Outras Saídas", IF(OR(ISNUMBER(SEARCH("CHEQUE COMPE SICREDI", F71)), ISNUMBER(SEARCH("aniversario", F71)), ISNUMBER(SEARCH("churrasco", F71)), ISNUMBER(SEARCH("bolo", F71)), ISNUMBER(SEARCH("SUPERMERCADO", F71))), "6.1 Despesas Administrativas (Pessoal)", IF(OR(ISNUMBER(SEARCH("DLKNET", F71)), ISNUMBER(SEARCH("TESTE", F71))), "6.1 Despesas Administrativas (Gerais)", IFERROR(VLOOKUP(H71, De_Para!A:B, 2, FALSE), "NÃO MAPEADO"))), IFERROR(VLOOKUP(H71, De_Para!A:B, 2, FALSE), "NÃO MAPEADO"))
A72: 69627 | B72: Sicredi SNI | C72: 29/06/2026 | D72: 26/06/2026 | E72: Débito em Conta | F72: TARIFA COM R LIQUIDACAO | G72: clau | H72: 02.03.03.09 : TARIFA COM R LIQUIDACAO | J72: -2.55 | K72: =IF(H72="02.09 : Outras Saídas", IF(OR(ISNUMBER(SEARCH("CHEQUE COMPE SICREDI", F72)), ISNUMBER(SEARCH("aniversario", F72)), ISNUMBER(SEARCH("churrasco", F72)), ISNUMBER(SEARCH("bolo", F72)), ISNUMBER(SEARCH("SUPERMERCADO", F72))), "6.1 Despesas Administrativas (Pessoal)", IF(OR(ISNUMBER(SEARCH("DLKNET", F72)), ISNUMBER(SEARCH("TESTE", F72))), "6.1 Despesas Administrativas (Gerais)", IFERROR(VLOOKUP(H72, De_Para!A:B, 2, FALSE), "NÃO MAPEADO"))), IFERROR(VLOOKUP(H72, De_Para!A:B, 2, FALSE), "NÃO MAPEADO"))
A73: 69626 | B73: Sicredi SNI | C73: 29/06/2026 | D73: 26/06/2026 | E73: Débito em Conta | F73: TARIFA COM R LIQUIDACAO | G73: clau | H73: 02.03.03.09 : TARIFA COM R LIQUIDACAO | J73: -1.7 | K73: =IF(H73="02.09 : Outras Saídas", IF(OR(ISNUMBER(SEARCH("CHEQUE COMPE SICREDI", F73)), ISNUMBER(SEARCH("aniversario", F73)), ISNUMBER(SEARCH("churrasco", F73)), ISNUMBER(SEARCH("bolo", F73)), ISNUMBER(SEARCH("SUPERMERCADO", F73))), "6.1 Despesas Administrativas (Pessoal)", IF(OR(ISNUMBER(SEARCH("DLKNET", F73)), ISNUMBER(SEARCH("TESTE", F73))), "6.1 Despesas Administrativas (Gerais)", IFERROR(VLOOKUP(H73, De_Para!A:B, 2, FALSE), "NÃO MAPEADO"))), IFERROR(VLOOKUP(H73, De_Para!A:B, 2, FALSE), "NÃO MAPEADO"))
A74: 69625 | B74: Sicredi SNI | C74: 29/06/2026 | D74: 26/06/2026 | E74: PIX | F74: PAGAMENTO PIX 29260889000128 Condominio Residenc Apartamento Curitiba | G74: clau | H74: 02.03.02.07 : Pro-Labore | J74: -650 | K74: =IF(H74="02.09 : Outras Saídas", IF(OR(ISNUMBER(SEARCH("CHEQUE COMPE SICREDI", F74)), ISNUMBER(SEARCH("aniversario", F74)), ISNUMBER(SEARCH("churrasco", F74)), ISNUMBER(SEARCH("bolo", F74)), ISNUMBER(SEARCH("SUPERMERCADO", F74))), "6.1 Despesas Administrativas (Pessoal)", IF(OR(ISNUMBER(SEARCH("DLKNET", F74)), ISNUMBER(SEARCH("TESTE", F74))), "6.1 Despesas Administrativas (Gerais)", IFERROR(VLOOKUP(H74, De_Para!A:B, 2, FALSE), "NÃO MAPEADO"))), IFERROR(VLOOKUP(H74, De_Para!A:B, 2, FALSE), "NÃO MAPEADO"))
A75: 69624 | B75: Sicredi SNI | C75: 29/06/2026 | D75: 26/06/2026 | E75: PIX | F75: PAGAMENTO PIX 04047379948 EVERTON ZILI DE AQUINO | G75: clau | H75: 02.03.02.07 : Pro-Labore | J75: -918 | K75: =IF(H75="02.09 : Outras Saídas", IF(OR(ISNUMBER(SEARCH("CHEQUE COMPE SICREDI", F75)), ISNUMBER(SEARCH("aniversario", F75)), ISNUMBER(SEARCH("churrasco", F75)), ISNUMBER(SEARCH("bolo", F75)), ISNUMBER(SEARCH("SUPERMERCADO", F75))), "6.1 Despesas Administrativas (Pessoal)", IF(OR(ISNUMBER(SEARCH("DLKNET", F75)), ISNUMBER(SEARCH("TESTE", F75))), "6.1 Despesas Administrativas (Gerais)", IFERROR(VLOOKUP(H75, De_Para!A:B, 2, FALSE), "NÃO MAPEADO"))), IFERROR(VLOOKUP(H75, De_Para!A:B, 2, FALSE), "NÃO MAPEADO"))
A76: 69623 | B76: Sicredi SNI | C76: 29/06/2026 | D76: 26/06/2026 | E76: Débito em Conta | F76: DEBITO CONVENIOS ID 0000066438705 COPEL DISTRIBU | G76: clau | H76: 02.03.02.04 : Energia Eletrica | J76: -687.96 | K76: =IF(H76="02.09 : Outras Saídas", IF(OR(ISNUMBER(SEARCH("CHEQUE COMPE SICREDI", F76)), ISNUMBER(SEARCH("aniversario", F76)), ISNUMBER(SEARCH("churrasco", F76)), ISNUMBER(SEARCH("bolo", F76)), ISNUMBER(SEARCH("SUPERMERCADO", F76))), "6.1 Despesas Administrativas (Pessoal)", IF(OR(ISNUMBER(SEARCH("DLKNET", F76)), ISNUMBER(SEARCH("TESTE", F76))), "6.1 Despesas Administrativas (Gerais)", IFERROR(VLOOKUP(H76, De_Para!A:B, 2, FALSE), "NÃO MAPEADO"))), IFERROR(VLOOKUP(H76, De_Para!A:B, 2, FALSE), "NÃO MAPEADO"))
A77: 69622 | B77: Sicredi SNI | C77: 29/06/2026 | D77: 29/06/2026 | E77: Cartão de Débito | F77: COMPRAS NACIONAIS CAFE E PADARIA PAO QUE Joaquim Bolo Aniversario Fabricinho | G77: clau | H77: 02.09 : Outras Saídas | J77: -109 | K77: =IF(H77="02.09 : Outras Saídas", IF(OR(ISNUMBER(SEARCH("CHEQUE COMPE SICREDI", F77)), ISNUMBER(SEARCH("aniversario", F77)), ISNUMBER(SEARCH("churrasco", F77)), ISNUMBER(SEARCH("bolo", F77)), ISNUMBER(SEARCH("SUPERMERCADO", F77))), "6.1 Despesas Administrativas (Pessoal)", IF(OR(ISNUMBER(SEARCH("DLKNET", F77)), ISNUMBER(SEARCH("TESTE", F77))), "6.1 Despesas Administrativas (Gerais)", IFERROR(VLOOKUP(H77, De_Para!A:B, 2, FALSE), "NÃO MAPEADO"))), IFERROR(VLOOKUP(H77, De_Para!A:B, 2, FALSE), "NÃO MAPEADO"))
A78: 69621 | B78: Sicredi SNI | C78: 29/06/2026 | D78: 29/06/2026 | E78: Cartão de Débito | F78: COMPRAS NACIONAIS DOCE SABOR JOAQUIM TAVORBR Marmitas Angelica | G78: clau | H78: 02.03.02.07 : Pro-Labore | J78: -79 | K78: =IF(H78="02.09 : Outras Saídas", IF(OR(ISNUMBER(SEARCH("CHEQUE COMPE SICREDI", F78)), ISNUMBER(SEARCH("aniversario", F78)), ISNUMBER(SEARCH("churrasco", F78)), ISNUMBER(SEARCH("bolo", F78)), ISNUMBER(SEARCH("SUPERMERCADO", F78))), "6.1 Despesas Administrativas (Pessoal)", IF(OR(ISNUMBER(SEARCH("DLKNET", F78)), ISNUMBER(SEARCH("TESTE", F78))), "6.1 Despesas Administrativas (Gerais)", IFERROR(VLOOKUP(H78, De_Para!A:B, 2, FALSE), "NÃO MAPEADO"))), IFERROR(VLOOKUP(H78, De_Para!A:B, 2, FALSE), "NÃO MAPEADO"))
A79: 69620 | B79: Sicredi SNI | C79: 29/06/2026 | D79: 29/06/2026 | E79: Cartão de Débito | F79: COMPRAS NACIONAIS SUPERMERCADO CARREIRO JOAQUIM churrasco Aniversario Fabricinho/jogo da copa | G79: clau | H79: 02.09 : Outras Saídas | J79: -335.31 | K79: =IF(H79="02.09 : Outras Saídas", IF(OR(ISNUMBER(SEARCH("CHEQUE COMPE SICREDI", F79)), ISNUMBER(SEARCH("aniversario", F79)), ISNUMBER(SEARCH("churrasco", F79)), ISNUMBER(SEARCH("bolo", F79)), ISNUMBER(SEARCH("SUPERMERCADO", F79))), "6.1 Despesas Administrativas (Pessoal)", IF(OR(ISNUMBER(SEARCH("DLKNET", F79)), ISNUMBER(SEARCH("TESTE", F79))), "6.1 Despesas Administrativas (Gerais)", IFERROR(VLOOKUP(H79, De_Para!A:B, 2, FALSE), "NÃO MAPEADO"))), IFERROR(VLOOKUP(H79, De_Para!A:B, 2, FALSE), "NÃO MAPEADO"))
A80: 69619 | B80: Sicredi SNI | C80: 29/06/2026 | D80: 29/06/2026 | E80: PIX | F80: Aparelho Luiza | G80: clau | H80: 02.03.02.07 : Pro-Labore | J80: -300 | K80: =IF(H80="02.09 : Outras Saídas", IF(OR(ISNUMBER(SEARCH("CHEQUE COMPE SICREDI", F80)), ISNUMBER(SEARCH("aniversario", F80)), ISNUMBER(SEARCH("churrasco", F80)), ISNUMBER(SEARCH("bolo", F80)), ISNUMBER(SEARCH("SUPERMERCADO", F80))), "6.1 Despesas Administrativas (Pessoal)", IF(OR(ISNUMBER(SEARCH("DLKNET", F80)), ISNUMBER(SEARCH("TESTE", F80))), "6.1 Despesas Administrativas (Gerais)", IFERROR(VLOOKUP(H80, De_Para!A:B, 2, FALSE), "NÃO MAPEADO"))), IFERROR(VLOOKUP(H80, De_Para!A:B, 2, FALSE), "NÃO MAPEADO"))
A81: 69618 | B81: Sicoob | C81: 29/06/2026 | D81: 29/06/2026 | E81: Dinheiro | F81: Boleto "54857" do cliente "NEIVA MARIA DA SILVA" | G81: system | H81: 02.03.02.01 : Cobrança Bancaria | J81: -0.88 | K81: =IF(H81="02.09 : Outras Saídas", IF(OR(ISNUMBER(SEARCH("CHEQUE COMPE SICREDI", F81)), ISNUMBER(SEARCH("aniversario", F81)), ISNUMBER(SEARCH("churrasco", F81)), ISNUMBER(SEARCH("bolo", F81)), ISNUMBER(SEARCH("SUPERMERCADO", F81))), "6.1 Despesas Administrativas (Pessoal)", IF(OR(ISNUMBER(SEARCH("DLKNET", F81)), ISNUMBER(SEARCH("TESTE", F81))), "6.1 Despesas Administrativas (Gerais)", IFERROR(VLOOKUP(H81, De_Para!A:B, 2, FALSE), "NÃO MAPEADO"))), IFERROR(VLOOKUP(H81, De_Para!A:B, 2, FALSE), "NÃO MAPEADO"))
A82: 69617 | B82: Sicoob | C82: 29/06/2026 | D82: 29/06/2026 | E82: Dinheiro | F82: Boleto "54857" do cliente "NEIVA MARIA DA SILVA" | G82: system | H82: 01.01.01 : Mensalidade | I82: 107.58 | K82: =IF(H82="02.09 : Outras Saídas", IF(OR(ISNUMBER(SEARCH("CHEQUE COMPE SICREDI", F82)), ISNUMBER(SEARCH("aniversario", F82)), ISNUMBER(SEARCH("churrasco", F82)), ISNUMBER(SEARCH("bolo", F82)), ISNUMBER(SEARCH("SUPERMERCADO", F82))), "6.1 Despesas Administrativas (Pessoal)", IF(OR(ISNUMBER(SEARCH("DLKNET", F82)), ISNUMBER(SEARCH("TESTE", F82))), "6.1 Despesas Administrativas (Gerais)", IFERROR(VLOOKUP(H82, De_Para!A:B, 2, FALSE), "NÃO MAPEADO"))), IFERROR(VLOOKUP(H82, De_Para!A:B, 2, FALSE), "NÃO MAPEADO"))
A83: 69616 | B83: Sicredi SNI | C83: 29/06/2026 | D83: 29/06/2026 | E83: PIX | F83: Boleto "54504" do cliente "THIARLES WILLIAN DA SILVA CORDEIRO" | G83: system | H83: 02.03.02.01 : Cobrança Bancaria | J83: -0.49 | K83: =IF(H83="02.09 : Outras Saídas", IF(OR(ISNUMBER(SEARCH("CHEQUE COMPE SICREDI", F83)), ISNUMBER(SEARCH("aniversario", F83)), ISNUMBER(SEARCH("churrasco", F83)), ISNUMBER(SEARCH("bolo", F83)), ISNUMBER(SEARCH("SUPERMERCADO", F83))), "6.1 Despesas Administrativas (Pessoal)", IF(OR(ISNUMBER(SEARCH("DLKNET", F83)), ISNUMBER(SEARCH("TESTE", F83))), "6.1 Despesas Administrativas (Gerais)", IFERROR(VLOOKUP(H83, De_Para!A:B, 2, FALSE), "NÃO MAPEADO"))), IFERROR(VLOOKUP(H83, De_Para!A:B, 2, FALSE), "NÃO MAPEADO"))
A84: 69615 | B84: Sicredi SNI | C84: 29/06/2026 | D84: 29/06/2026 | E84: PIX | F84: Boleto "54504" do cliente "THIARLES WILLIAN DA SILVA CORDEIRO" | G84: system | H84: 01.01.01 : Mensalidade | I84: 112.38 | K84: =IF(H84="02.09 : Outras Saídas", IF(OR(ISNUMBER(SEARCH("CHEQUE COMPE SICREDI", F84)), ISNUMBER(SEARCH("aniversario", F84)), ISNUMBER(SEARCH("churrasco", F84)), ISNUMBER(SEARCH("bolo", F84)), ISNUMBER(SEARCH("SUPERMERCADO", F84))), "6.1 Despesas Administrativas (Pessoal)", IF(OR(ISNUMBER(SEARCH("DLKNET", F84)), ISNUMBER(SEARCH("TESTE", F84))), "6.1 Despesas Administrativas (Gerais)", IFERROR(VLOOKUP(H84, De_Para!A:B, 2, FALSE), "NÃO MAPEADO"))), IFERROR(VLOOKUP(H84, De_Para!A:B, 2, FALSE), "NÃO MAPEADO"))
A85: 69614 | B85: Sicredi SNI | C85: 29/06/2026 | D85: 29/06/2026 | E85: Dinheiro | F85: Boleto "54966" do cliente "HELENA MARIA PEREIRA" | G85: system | H85: 02.03.02.01 : Cobrança Bancaria | J85: -1.08 | K85: =IF(H85="02.09 : Outras Saídas", IF(OR(ISNUMBER(SEARCH("CHEQUE COMPE SICREDI", F85)), ISNUMBER(SEARCH("aniversario", F85)), ISNUMBER(SEARCH("churrasco", F85)), ISNUMBER(SEARCH("bolo", F85)), ISNUMBER(SEARCH("SUPERMERCADO", F85))), "6.1 Despesas Administrativas (Pessoal)", IF(OR(ISNUMBER(SEARCH("DLKNET", F85)), ISNUMBER(SEARCH("TESTE", F85))), "6.1 Despesas Administrativas (Gerais)", IFERROR(VLOOKUP(H85, De_Para!A:B, 2, FALSE), "NÃO MAPEADO"))), IFERROR(VLOOKUP(H85, De_Para!A:B, 2, FALSE), "NÃO MAPEADO"))
A86: 69613 | B86: Sicredi SNI | C86: 29/06/2026 | D86: 29/06/2026 | E86: Dinheiro | F86: Boleto "54966" do cliente "HELENA MARIA PEREIRA" | G86: system | H86: 01.01.01 : Mensalidade | I86: 102.27 | K86: =IF(H86="02.09 : Outras Saídas", IF(OR(ISNUMBER(SEARCH("CHEQUE COMPE SICREDI", F86)), ISNUMBER(SEARCH("aniversario", F86)), ISNUMBER(SEARCH("churrasco", F86)), ISNUMBER(SEARCH("bolo", F86)), ISNUMBER(SEARCH("SUPERMERCADO", F86))), "6.1 Despesas Administrativas (Pessoal)", IF(OR(ISNUMBER(SEARCH("DLKNET", F86)), ISNUMBER(SEARCH("TESTE", F86))), "6.1 Despesas Administrativas (Gerais)", IFERROR(VLOOKUP(H86, De_Para!A:B, 2, FALSE), "NÃO MAPEADO"))), IFERROR(VLOOKUP(H86, De_Para!A:B, 2, FALSE), "NÃO MAPEADO"))
A87: 69612 | B87: Sicoob | C87: 29/06/2026 | D87: 29/06/2026 | E87: Dinheiro | F87: Boleto "66783" do cliente "PIETRO NATANAEL DA SILVA VIDAL" | G87: system | H87: 02.03.02.01 : Cobrança Bancaria | J87: -0.88 | K87: =IF(H87="02.09 : Outras Saídas", IF(OR(ISNUMBER(SEARCH("CHEQUE COMPE SICREDI", F87)), ISNUMBER(SEARCH("aniversario", F87)), ISNUMBER(SEARCH("churrasco", F87)), ISNUMBER(SEARCH("bolo", F87)), ISNUMBER(SEARCH("SUPERMERCADO", F87))), "6.1 Despesas Administrativas (Pessoal)", IF(OR(ISNUMBER(SEARCH("DLKNET", F87)), ISNUMBER(SEARCH("TESTE", F87))), "6.1 Despesas Administrativas (Gerais)", IFERROR(VLOOKUP(H87, De_Para!A:B, 2, FALSE), "NÃO MAPEADO"))), IFERROR(VLOOKUP(H87, De_Para!A:B, 2, FALSE), "NÃO MAPEADO"))
A88: 69611 | B88: Sicoob | C88: 29/06/2026 | D88: 29/06/2026 | E88: Dinheiro | F88: Boleto "66783" do cliente "PIETRO NATANAEL DA SILVA VIDAL" | G88: system | H88: 01.01.01 : Mensalidade | I88: 109.9 | K88: =IF(H88="02.09 : Outras Saídas", IF(OR(ISNUMBER(SEARCH("CHEQUE COMPE SICREDI", F88)), ISNUMBER(SEARCH("aniversario", F88)), ISNUMBER(SEARCH("churrasco", F88)), ISNUMBER(SEARCH("bolo", F88)), ISNUMBER(SEARCH("SUPERMERCADO", F88))), "6.1 Despesas Administrativas (Pessoal)", IF(OR(ISNUMBER(SEARCH("DLKNET", F88)), ISNUMBER(SEARCH("TESTE", F88))), "6.1 Despesas Administrativas (Gerais)", IFERROR(VLOOKUP(H88, De_Para!A:B, 2, FALSE), "NÃO MAPEADO"))), IFERROR(VLOOKUP(H88, De_Para!A:B, 2, FALSE), "NÃO MAPEADO"))
A89: 69610 | B89: Sicoob | C89: 29/06/2026 | D89: 29/06/2026 | E89: Dinheiro | F89: Boleto "65983" do cliente "GILMAR BATISTA DA SILVA" | G89: system | H89: 02.03.02.01 : Cobrança Bancaria | J89: -0.88 | K89: =IF(H89="02.09 : Outras Saídas", IF(OR(ISNUMBER(SEARCH("CHEQUE COMPE SICREDI", F89)), ISNUMBER(SEARCH("aniversario", F89)), ISNUMBER(SEARCH("churrasco", F89)), ISNUMBER(SEARCH("bolo", F89)), ISNUMBER(SEARCH("SUPERMERCADO", F89))), "6.1 Despesas Administrativas (Pessoal)", IF(OR(ISNUMBER(SEARCH("DLKNET", F89)), ISNUMBER(SEARCH("TESTE", F89))), "6.1 Despesas Administrativas (Gerais)", IFERROR(VLOOKUP(H89, De_Para!A:B, 2, FALSE), "NÃO MAPEADO"))), IFERROR(VLOOKUP(H89, De_Para!A:B, 2, FALSE), "NÃO MAPEADO"))
A90: 69609 | B90: Sicoob | C90: 29/06/2026 | D90: 29/06/2026 | E90: Dinheiro | F90: Boleto "65983" do cliente "GILMAR BATISTA DA SILVA" | G90: system | H90: 01.01.01 : Mensalidade | I90: 104.9 | K90: =IF(H90="02.09 : Outras Saídas", IF(OR(ISNUMBER(SEARCH("CHEQUE COMPE SICREDI", F90)), ISNUMBER(SEARCH("aniversario", F90)), ISNUMBER(SEARCH("churrasco", F90)), ISNUMBER(SEARCH("bolo", F90)), ISNUMBER(SEARCH("SUPERMERCADO", F90))), "6.1 Despesas Administrativas (Pessoal)", IF(OR(ISNUMBER(SEARCH("DLKNET", F90)), ISNUMBER(SEARCH("TESTE", F90))), "6.1 Despesas Administrativas (Gerais)", IFERROR(VLOOKUP(H90, De_Para!A:B, 2, FALSE), "NÃO MAPEADO"))), IFERROR(VLOOKUP(H90, De_Para!A:B, 2, FALSE), "NÃO MAPEADO"))
A91: 69608 | B91: Sicoob | C91: 29/06/2026 | D91: 29/06/2026 | E91: Dinheiro | F91: Boleto "65972" do cliente "EFRAIN DE CARVALHO PAULA" | G91: system | H91: 02.03.02.01 : Cobrança Bancaria | J91: -0.88 | K91: =IF(H91="02.09 : Outras Saídas", IF(OR(ISNUMBER(SEARCH("CHEQUE COMPE SICREDI", F91)), ISNUMBER(SEARCH("aniversario", F91)), ISNUMBER(SEARCH("churrasco", F91)), ISNUMBER(SEARCH("bolo", F91)), ISNUMBER(SEARCH("SUPERMERCADO", F91))), "6.1 Despesas Administrativas (Pessoal)", IF(OR(ISNUMBER(SEARCH("DLKNET", F91)), ISNUMBER(SEARCH("TESTE", F91))), "6.1 Despesas Administrativas (Gerais)", IFERROR(VLOOKUP(H91, De_Para!A:B, 2, FALSE), "NÃO MAPEADO"))), IFERROR(VLOOKUP(H91, De_Para!A:B, 2, FALSE), "NÃO MAPEADO"))
A92: 69607 | B92: Sicoob | C92: 29/06/2026 | D92: 29/06/2026 | E92: Dinheiro | F92: Boleto "65972" do cliente "EFRAIN DE CARVALHO PAULA" | G92: system | H92: 01.03.01 : Mensalidade | I92: 107.41 | K92: =IF(H92="02.09 : Outras Saídas", IF(OR(ISNUMBER(SEARCH("CHEQUE COMPE SICREDI", F92)), ISNUMBER(SEARCH("aniversario", F92)), ISNUMBER(SEARCH("churrasco", F92)), ISNUMBER(SEARCH("bolo", F92)), ISNUMBER(SEARCH("SUPERMERCADO", F92))), "6.1 Despesas Administrativas (Pessoal)", IF(OR(ISNUMBER(SEARCH("DLKNET", F92)), ISNUMBER(SEARCH("TESTE", F92))), "6.1 Despesas Administrativas (Gerais)", IFERROR(VLOOKUP(H92, De_Para!A:B, 2, FALSE), "NÃO MAPEADO"))), IFERROR(VLOOKUP(H92, De_Para!A:B, 2, FALSE), "NÃO MAPEADO"))
A93: 69606 | B93: Sicoob | C93: 29/06/2026 | D93: 29/06/2026 | E93: Dinheiro | F93: Boleto "65374" do cliente "ROSENILDA INOCENCIA ANACLETO" | G93: system | H93: 02.03.02.01 : Cobrança Bancaria | J93: -0.88 | K93: =IF(H93="02.09 : Outras Saídas", IF(OR(ISNUMBER(SEARCH("CHEQUE COMPE SICREDI", F93)), ISNUMBER(SEARCH("aniversario", F93)), ISNUMBER(SEARCH("churrasco", F93)), ISNUMBER(SEARCH("bolo", F93)), ISNUMBER(SEARCH("SUPERMERCADO", F93))), "6.1 Despesas Administrativas (Pessoal)", IF(OR(ISNUMBER(SEARCH("DLKNET", F93)), ISNUMBER(SEARCH("TESTE", F93))), "6.1 Despesas Administrativas (Gerais)", IFERROR(VLOOKUP(H93, De_Para!A:B, 2, FALSE), "NÃO MAPEADO"))), IFERROR(VLOOKUP(H93, De_Para!A:B, 2, FALSE), "NÃO MAPEADO"))
A94: 69605 | B94: Sicoob | C94: 29/06/2026 | D94: 29/06/2026 | E94: Dinheiro | F94: Boleto "65374" do cliente "ROSENILDA INOCENCIA ANACLETO" | G94: system | H94: 01.01.01 : Mensalidade | I94: 110 | K94: =IF(H94="02.09 : Outras Saídas", IF(OR(ISNUMBER(SEARCH("CHEQUE COMPE SICREDI", F94)), ISNUMBER(SEARCH("aniversario", F94)), ISNUMBER(SEARCH("churrasco", F94)), ISNUMBER(SEARCH("bolo", F94)), ISNUMBER(SEARCH("SUPERMERCADO", F94))), "6.1 Despesas Administrativas (Pessoal)", IF(OR(ISNUMBER(SEARCH("DLKNET", F94)), ISNUMBER(SEARCH("TESTE", F94))), "6.1 Despesas Administrativas (Gerais)", IFERROR(VLOOKUP(H94, De_Para!A:B, 2, FALSE), "NÃO MAPEADO"))), IFERROR(VLOOKUP(H94, De_Para!A:B, 2, FALSE), "NÃO MAPEADO"))
A95: 69604 | B95: Sicoob | C95: 29/06/2026 | D95: 29/06/2026 | E95: Dinheiro | F95: Boleto "61483" do cliente "SEBASTIAO INOCENCIO DE MORAIS" | G95: system | H95: 02.03.02.01 : Cobrança Bancaria | J95: -0.88 | K95: =IF(H95="02.09 : Outras Saídas", IF(OR(ISNUMBER(SEARCH("CHEQUE COMPE SICREDI", F95)), ISNUMBER(SEARCH("aniversario", F95)), ISNUMBER(SEARCH("churrasco", F95)), ISNUMBER(SEARCH("bolo", F95)), ISNUMBER(SEARCH("SUPERMERCADO", F95))), "6.1 Despesas Administrativas (Pessoal)", IF(OR(ISNUMBER(SEARCH("DLKNET", F95)), ISNUMBER(SEARCH("TESTE", F95))), "6.1 Despesas Administrativas (Gerais)", IFERROR(VLOOKUP(H95, De_Para!A:B, 2, FALSE), "NÃO MAPEADO"))), IFERROR(VLOOKUP(H95, De_Para!A:B, 2, FALSE), "NÃO MAPEADO"))
A96: 69603 | B96: Sicoob | C96: 29/06/2026 | D96: 29/06/2026 | E96: Dinheiro | F96: Boleto "61483" do cliente "SEBASTIAO INOCENCIO DE MORAIS" | G96: system | H96: 01.01.01 : Mensalidade | I96: 105 | K96: =IF(H96="02.09 : Outras Saídas", IF(OR(ISNUMBER(SEARCH("CHEQUE COMPE SICREDI", F96)), ISNUMBER(SEARCH("aniversario", F96)), ISNUMBER(SEARCH("churrasco", F96)), ISNUMBER(SEARCH("bolo", F96)), ISNUMBER(SEARCH("SUPERMERCADO", F96))), "6.1 Despesas Administrativas (Pessoal)", IF(OR(ISNUMBER(SEARCH("DLKNET", F96)), ISNUMBER(SEARCH("TESTE", F96))), "6.1 Despesas Administrativas (Gerais)", IFERROR(VLOOKUP(H96, De_Para!A:B, 2, FALSE), "NÃO MAPEADO"))), IFERROR(VLOOKUP(H96, De_Para!A:B, 2, FALSE), "NÃO MAPEADO"))
A97: 69602 | B97: Sicoob | C97: 29/06/2026 | D97: 29/06/2026 | E97: Dinheiro | F97: Boleto "54879" do cliente "SIMONE MIRANDA OLIVEIRA" | G97: system | H97: 02.03.02.01 : Cobrança Bancaria | J97: -0.88 | K97: =IF(H97="02.09 : Outras Saídas", IF(OR(ISNUMBER(SEARCH("CHEQUE COMPE SICREDI", F97)), ISNUMBER(SEARCH("aniversario", F97)), ISNUMBER(SEARCH("churrasco", F97)), ISNUMBER(SEARCH("bolo", F97)), ISNUMBER(SEARCH("SUPERMERCADO", F97))), "6.1 Despesas Administrativas (Pessoal)", IF(OR(ISNUMBER(SEARCH("DLKNET", F97)), ISNUMBER(SEARCH("TESTE", F97))), "6.1 Despesas Administrativas (Gerais)", IFERROR(VLOOKUP(H97, De_Para!A:B, 2, FALSE), "NÃO MAPEADO"))), IFERROR(VLOOKUP(H97, De_Para!A:B, 2, FALSE), "NÃO MAPEADO"))
A98: 69601 | B98: Sicoob | C98: 29/06/2026 | D98: 29/06/2026 | E98: Dinheiro | F98: Boleto "54879" do cliente "SIMONE MIRANDA OLIVEIRA" | G98: system | H98: 01.01.01 : Mensalidade | I98: 107.41 | K98: =IF(H98="02.09 : Outras Saídas", IF(OR(ISNUMBER(SEARCH("CHEQUE COMPE SICREDI", F98)), ISNUMBER(SEARCH("aniversario", F98)), ISNUMBER(SEARCH("churrasco", F98)), ISNUMBER(SEARCH("bolo", F98)), ISNUMBER(SEARCH("SUPERMERCADO", F98))), "6.1 Despesas Administrativas (Pessoal)", IF(OR(ISNUMBER(SEARCH("DLKNET", F98)), ISNUMBER(SEARCH("TESTE", F98))), "6.1 Despesas Administrativas (Gerais)", IFERROR(VLOOKUP(H98, De_Para!A:B, 2, FALSE), "NÃO MAPEADO"))), IFERROR(VLOOKUP(H98, De_Para!A:B, 2, FALSE), "NÃO MAPEADO"))
A99: 69600 | B99: Sicredi SNI | C99: 29/06/2026 | D99: 29/06/2026 | E99: PIX | F99: Boleto "55010" do cliente "CLAUDINEIA SABINO LOURENÇO ALVES" | G99: system | H99: 02.03.02.01 : Cobrança Bancaria | J99: -0.49 | K99: =IF(H99="02.09 : Outras Saídas", IF(OR(ISNUMBER(SEARCH("CHEQUE COMPE SICREDI", F99)), ISNUMBER(SEARCH("aniversario", F99)), ISNUMBER(SEARCH("churrasco", F99)), ISNUMBER(SEARCH("bolo", F99)), ISNUMBER(SEARCH("SUPERMERCADO", F99))), "6.1 Despesas Administrativas (Pessoal)", IF(OR(ISNUMBER(SEARCH("DLKNET", F99)), ISNUMBER(SEARCH("TESTE", F99))), "6.1 Despesas Administrativas (Gerais)", IFERROR(VLOOKUP(H99, De_Para!A:B, 2, FALSE), "NÃO MAPEADO"))), IFERROR(VLOOKUP(H99, De_Para!A:B, 2, FALSE), "NÃO MAPEADO"))
A100: 69599 | B100: Sicredi SNI | C100: 29/06/2026 | D100: 29/06/2026 | E100: PIX | F100: Boleto "55010" do cliente "CLAUDINEIA SABINO LOURENÇO ALVES" | G100: system | H100: 01.01.01 : Mensalidade | I100: 105 | K100: =IF(H100="02.09 : Outras Saídas", IF(OR(ISNUMBER(SEARCH("CHEQUE COMPE SICREDI", F100)), ISNUMBER(SEARCH("aniversario", F100)), ISNUMBER(SEARCH("churrasco", F100)), ISNUMBER(SEARCH("bolo", F100)), ISNUMBER(SEARCH("SUPERMERCADO", F100))), "6.1 Despesas Administrativas (Pessoal)", IF(OR(ISNUMBER(SEARCH("DLKNET", F100)), ISNUMBER(SEARCH("TESTE", F100))), "6.1 Despesas Administrativas (Gerais)", IFERROR(VLOOKUP(H100, De_Para!A:B, 2, FALSE), "NÃO MAPEADO"))), IFERROR(VLOOKUP(H100, De_Para!A:B, 2, FALSE), "NÃO MAPEADO"))
...

Sheet De_Para
A1: Plano de Contas ERP | B1: Categoria DRE
A2: 01.01.01 : Mensalidade | B2: 1.2 Receita de Internet (SVA)
A3: 01.01.02 : Adesão | B3: 1.3 Taxas de Instalação e Adesão
A4: 01.01.03.03 : VALE ALIMENTAÇÃO | B4: 6.1 Despesas Administrativas (Pessoal)
A5: 01.03.01 : Mensalidade | B5: 1.2 Receita de Internet (SVA)
A6: 01.03.02 : Adesão | B6: 1.3 Taxas de Instalação e Adesão
A7: 01.05.02 : Adesão | B7: 1.3 Taxas de Instalação e Adesão
A8: 01.50.02 : Equipamentos | B8: 1.4 Outras Receitas (Equipamentos)
A9: 01.60.01 : Serviço de reparo e manutenção | B9: 1.4 Outras Receitas (Serviços Avulsos)
A10: 01.90 : Outras Entradas | B10: 1.4 Outras Receitas (Diversas)
A11: 02,07 : DÉB.EMPRÉSTIMO | B11: 8.1 Amortização de Empréstimos e Financiamentos
A12: 02.01.02.01 : Folha de Pagamento | B12: 6.1 Despesas Administrativas (Pessoal)
... A48: TRANSF.ENTRE CONTAS : 02.12 | B48: EXCLUÍDO DA DRE

Sheet DRE
A1: DEMONSTRATIVO DE RESULTADOS DO EXERCÍCIO - DRE
A2: Provedor de Internet (ISP) - Relatório Gerencial Dinâmico
A4: Estrutura do Plano de Contas | B4: Valor (R$) | C4: % Rec. Bruta
A5: 1. RECEITA OPERACIONAL BRUTA | B5: =SUM(B6:B10)
A6: 1.2 Receita de Internet (SVA) | B6: =SUMIFS(Lançamentos!I:I, Lançamentos!K:K, "1.2 Receita de Internet (SVA)") | C6: =B6/$B$11
A7: 1.3 Taxas de Instalação e Adesão | B7: =SUMIFS(Lançamentos!I:I, Lançamentos!K:K, "1.3 Taxas de Instalação e Adesão") | C7: =B7/$B$11
A8: 1.4 Outras Receitas (Equipamentos) | B8: =SUMIFS(Lançamentos!I:I, Lançamentos!K:K, "1.4 Outras Receitas (Equipamentos)") | C8: =B8/$B$11
A9: 1.4 Outras Receitas (Serviços Avulsos) | B9: =SUMIFS(Lançamentos!I:I, Lançamentos!K:K, "1.4 Outras Receitas (Serviços Avulsos)") | C9: =B9/$B$11
A10: 1.4 Outras Receitas (Diversas) | B10: =SUMIFS(Lançamentos!I:I, Lançamentos!K:K, "1.4 Outras Receitas (Diversas)") | C10: =B10/$B$11
A11: (=) Total Receita Bruta | B11: =SUM(B6:B10) | C11: =B11/$B$11
A12: 2. (-) DEDUÇÕES E TRIBUTOS | B12: =B14
A13: 2.1 Tributos sobre Serviços (DARF) | B13: =-SUMIFS(Lançamentos!J:J, Lançamentos!K:K, "2.1 Tributos sobre Serviços (DARF)") | C13: =B13/$B$11
A14: (=) Total Deduções | B14: =B13 | C14: =B14/$B$11
A15: 3. (=) RECEITA OPERACIONAL LÍQUIDA (ROL) | B15: =B11-B14 | C15: =B15/$B$11
A16: 4. (-) CUSTOS DOS SERVIÇOS PRESTADOS (CSP) | B16: =B20
A17: 4.1 Links Dedicados / Trânsito IP | B17: =-SUMIFS(Lançamentos!J:J, Lançamentos!K:K, "4.1 Links Dedicados / Trânsito IP") | C17: =B17/$B$11
A18: 4.2 Postes e Aluguel de Infraestrutura | B18: =-SUMIFS(Lançamentos!J:J, Lançamentos!K:K, "4.2 Postes e Aluguel de Infraestrutura") | C18: =B18/$B$11
A19: 4.5 Manutenção de Rede / Licenças Técnicas | B19: =-SUMIFS(Lançamentos!J:J, Lançamentos!K:K, "4.5 Manutenção de Rede / Licenças Técnicas") | C19: =B19/$B$11
A20: (=) Total Custos (CSP) | B20: =SUM(B17:B19) | C20: =B20/$B$11
A21: 5. (=) MARGEM DE CONTRIBUIÇÃO / LUCRO BRUTO | B21: =B15-B20 | C21: =B21/$B$11
A22: 6. (-) DESPESAS OPERACIONAIS (OPEX) | B22: =B30
A23: 6.1 Despesas Administrativas (Pessoal) | B23: =-SUMIFS(Lançamentos!J:J, Lançamentos!K:K, "6.1 Despesas Administrativas (Pessoal)") | C23: =B23/$B$11
A24: 6.1 Despesas Administrativas (Infra) | B24: =-SUMIFS(Lançamentos!J:J, Lançamentos!K:K, "6.1 Despesas Administrativas (Infra)") | C24: =B24/$B$11
A25: 6.1 Despesas Administrativas (Gerais) | B25: =-SUMIFS(Lançamentos!J:J, Lançamentos!K:K, "6.1 Despesas Administrativas (Gerais)") | C25: =B25/$B$11
A26: 6.3 Despesas Financeiras (Taxas Boleto) | B26: =-SUMIFS(Lançamentos!J:J, Lançamentos!K:K, "6.3 Despesas Financeiras (Taxas Boleto)") | C26: =B26/$B$11
A27: 6.3 Despesas Financeiras (Gerais) | B27: =-SUMIFS(Lançamentos!J:J, Lançamentos!K:K, "6.3 Despesas Financeiras (Gerais)") | C27: =B27/$B$11
A28: 6.3 Despesas Financeiras (Encargos) | B28: =-SUMIFS(Lançamentos!J:J, Lançamentos!K:K, "6.3 Despesas Financeiras (Encargos)") | C28: =B28/$B$11
A29: 6.4 Outras Despesas Operacionais | B29: =-SUMIFS(Lançamentos!J:J, Lançamentos!K:K, "6.4 Outras Despesas Operacionais") | C29: =B29/$B$11
A30: (=) Total Despesas (OPEX) | B30: =SUM(B23:B29) | C30: =B30/$B$11
A31: 7. (=) RESULTADO OPERACIONAL (EBITDA) | B31: =B21-B30 | C31: =B31/$B$11
A32: 8. (-) AMORTIZAÇÃO E OUTROS | B32: =B34
A33: 8.1 Amortização de Empréstimos e Financiamentos | B33: =-SUMIFS(Lançamentos!J:J, Lançamentos!K:K, "8.1 Amortização de Empréstimos e Financiamentos") | C33: =B33/$B$11
A34: (=) Total Amortização | B34: =B33 | C34: =B34/$B$11
A35: 9. (=) RESULTADO LÍQUIDO DO EXERCÍCIO | B35: =B31-B34 | C35: =B35/$B$11
